{
  "student_id": "did:example:STU002",
  "term_id": "Fall_2023",
  "courses": [
    {
      "issuer_id": "IU-MATH",
      "student_id": "STU002",
      "term_id": "Fall_2023",
      "course_id": "BUS101",
      "course_name": "Business Fundamentals",
      "attempt_no": 1,
      "started_at": "2023-09-16T00:12:19.919940031Z",
      "completed_at": "2023-11-04T07:16:42.081521219Z",
      "assessed_at": "2023-11-08T07:16:42.081521219Z",
      "issued_at": "2023-11-16T07:16:42.081521219Z",
      "grade": "D+",
      "credits": 3,
      "instructor": "Prof. Johnson"
    },
    {
      "issuer_id": "IU-CS",
      "student_id": "STU002",
      "term_id": "Fall_2023",
      "course_id": "BUS101",
      "course_name": "Business Fundamentals",
      "attempt_no": 1,
      "started_at": "2023-09-22T17:05:51.823216784Z",
      "completed_at": "2023-11-17T10:37:00.111304236Z",
      "assessed_at": "2023-11-21T10:37:00.111304236Z",
      "issued_at": "2023-11-24T10:37:00.111304236Z",
      "grade": "A+",
      "credits": 3,
      "instructor": "Prof. Taylor"
    },
    {
      "issuer_id": "IU-CHEM",
      "student_id": "STU002",
      "term_id": "Fall_2023",
      "course_id": "MATH201",
      "course_name": "Linear Algebra",
      "attempt_no": 1,
      "started_at": "2023-09-25T00:44:22.93485439Z",
      "completed_at": "2023-11-15T15:34:17.685876218Z",
      "assessed_at": "2023-11-21T15:34:17.685876218Z",
      "issued_at": "2023-11-27T15:34:17.685876218Z",
      "grade": "A-",
      "credits": 3,
      "instructor": "Prof. Anderson"
    },
    {
      "issuer_id": "IU-MATH",
      "student_id": "STU002",
      "term_id": "Fall_2023",
      "course_id": "MATH201",
      "course_name": "Linear Algebra",
      "attempt_no": 1,
      "started_at": "2023-09-01T13:26:05.840535968Z",
      "completed_at": "2023-11-20T12:44:30.785264545Z",
      "assessed_at": "2023-11-24T12:44:30.785264545Z",
      "issued_at": "2023-12-02T12:44:30.785264545Z",
      "grade": "D",
      "credits": 3,
      "instructor": "Prof. Miller"
    }
  ],
  "root": [
    113,
    213,
    50,
    188,
    22,
    151,
    194,
    200,
    123,
    148,
    103,
    203,
    109,
    20,
    162,
    244,
    184,
    126,
    72,
    235,
    115,
    7,
    55,
    9,
    245,
    173,
    244,
    16,
    176,
    24,
    251,
    137
  ],
  "leaves": [
    {
      "course": {
        "issuer_id": "IU-MATH",
        "student_id": "STU002",
        "term_id": "Fall_2023",
        "course_id": "BUS101",
        "course_name": "Business Fundamentals",
        "attempt_no": 1,
        "started_at": "2023-09-16T00:12:19.919940031Z",
        "completed_at": "2023-11-04T07:16:42.081521219Z",
        "assessed_at": "2023-11-08T07:16:42.081521219Z",
        "issued_at": "2023-11-16T07:16:42.081521219Z",
        "grade": "D+",
        "credits": 3,
        "instructor": "Prof. Johnson"
      },
      "timestamp32": [
        0,
        0,
        0,
        0,
        101,
        4,
        242,
        227,
        0,
        0,
        0,
        0,
        101,
        69,
        239,
        218,
        0,
        0,
        0,
        0,
        101,
        75,
        53,
        218,
        0,
        0,
        0,
        0,
        101,
        85,
        193,
        218
      ],
      "course_hash32": [
        157,
        94,
        136,
        200,
        63,
        223,
        213,
        107,
        86,
        46,
        87,
        195,
        130,
        31,
        217,
        23,
        216,
        231,
        191,
        164,
        209,
        8,
        243,
        95,
        76,
        138,
        148,
        36,
        10,
        147,
        2,
        54
      ]
    },
    {
      "course": {
        "issuer_id": "IU-CS",
        "student_id": "STU002",
        "term_id": "Fall_2023",
        "course_id": "BUS101",
        "course_name": "Business Fundamentals",
        "attempt_no": 1,
        "started_at": "2023-09-22T17:05:51.823216784Z",
        "completed_at": "2023-11-17T10:37:00.111304236Z",
        "assessed_at": "2023-11-21T10:37:00.111304236Z",
        "issued_at": "2023-11-24T10:37:00.111304236Z",
        "grade": "A+",
        "credits": 3,
        "instructor": "Prof. Taylor"
      },
      "timestamp32": [
        0,
        0,
        0,
        0,
        101,
        13,
        201,
        111,
        0,
        0,
        0,
        0,
        101,
        87,
        66,
        76,
        0,
        0,
        0,
        0,
        101,
        92,
        136,
        76,
        0,
        0,
        0,
        0,
        101,
        96,
        124,
        204
      ],
      "course_hash32": [
        10,
        103,
        81,
        153,
        209,
        2,
        122,
        116,
        155,
        242,
        15,
        163,
        85,
        112,
        98,
        2,
        63,
        117,
        111,
        139,
        230,
        137,
        195,
        27,
        33,
        237,
        162,
        61,
        159,
        246,
        153,
        75
      ]
    },
    {
      "course": {
        "issuer_id": "IU-CHEM",
        "student_id": "STU002",
        "term_id": "Fall_2023",
        "course_id": "MATH201",
        "course_name": "Linear Algebra",
        "attempt_no": 1,
        "started_at": "2023-09-25T00:44:22.93485439Z",
        "completed_at": "2023-11-15T15:34:17.685876218Z",
        "assessed_at": "2023-11-21T15:34:17.685876218Z",
        "issued_at": "2023-11-27T15:34:17.685876218Z",
        "grade": "A-",
        "credits": 3,
        "instructor": "Prof. Anderson"
      },
      "timestamp32": [
        0,
        0,
        0,
        0,
        101,
        16,
        215,
        230,
        0,
        0,
        0,
        0,
        101,
        84,
        228,
        249,
        0,
        0,
        0,
        0,
        101,
        92,
        205,
        249,
        0,
        0,
        0,
        0,
        101,
        100,
        182,
        249
      ],
      "course_hash32": [
        5,
        116,
        55,
        87,
        52,
        218,
        201,
        49,
        69,
        112,
        160,
        235,
        177,
        20,
        237,
        236,
        166,
        211,
        190,
        104,
        174,
        0,
        109,
        28,
        88,
        87,
        217,
        103,
        150,
        158,
        87,
        50
      ]
    },
    {
      "course": {
        "issuer_id": "IU-MATH",
        "student_id": "STU002",
        "term_id": "Fall_2023",
        "course_id": "MATH201",
        "course_name": "Linear Algebra",
        "attempt_no": 1,
        "started_at": "2023-09-01T13:26:05.840535968Z",
        "completed_at": "2023-11-20T12:44:30.785264545Z",
        "assessed_at": "2023-11-24T12:44:30.785264545Z",
        "issued_at": "2023-12-02T12:44:30.785264545Z",
        "grade": "D",
        "credits": 3,
        "instructor": "Prof. Miller"
      },
      "timestamp32": [
        0,
        0,
        0,
        0,
        100,
        241,
        230,
        109,
        0,
        0,
        0,
        0,
        101,
        91,
        84,
        174,
        0,
        0,
        0,
        0,
        101,
        96,
        154,
        174,
        0,
        0,
        0,
        0,
        101,
        107,
        38,
        174
      ],
      "course_hash32": [
        194,
        54,
        220,
        192,
        112,
        79,
        201,
        183,
        149,
        252,
        131,
        37,
        254,
        243,
        216,
        205,
        159,
        89,
        212,
        79,
        16,
        119,
        180,
        7,
        195,
        62,
        66,
        254,
        218,
        228,
        95,
        85
      ]
    }
  ],
  "proofs": {
    "BUS101": [
      "31308419fdb635a7d7210ff4e7dad8b0dec8a4f894f8efa7268f01e383365775",
      "08ec184c8cfe2dd4a2bebbf9eaaad330497e3c1714281b7ca635b7ea0722cac9"
    ],
    "MATH201": [
      "9c38983821482ca46228790371944b1a14a19e8bb79c6b2681b37ad104eb7cca",
      "e38bd5ca0342c98774efc5021cd40b5e8dbc303a7a2d1aa85dc728f67c8c7d36"
    ]
  }
}