{
  "student_id": "did:example:ITITIU00033",
  "term_id": "Semester_2_2024",
  "courses": [
    {
      "issuer_id": "IU-CHEM",
      "student_id": "ITITIU00033",
      "term_id": "Semester_2_2024",
      "course_id": "CH011IU",
      "course_name": "Chemistry for Engineers",
      "attempt_no": 1,
      "started_at": "2025-01-28T16:30:20.096317361Z",
      "completed_at": "2025-03-29T10:33:10.069927988Z",
      "assessed_at": "2025-04-01T10:33:10.069927988Z",
      "issued_at": "2025-04-15T10:33:10.069927988Z",
      "grade": "C+",
      "credits": 3,
      "instructor": "Prof. Davis"
    },
    {
      "issuer_id": "IU-CS",
      "student_id": "ITITIU00033",
      "term_id": "Semester_2_2024",
      "course_id": "MA001IU",
      "course_name": "Calculus 1",
      "attempt_no": 1,
      "started_at": "2025-01-16T14:04:54.316561317Z",
      "completed_at": "2025-03-26T09:49:55.623841857Z",
      "assessed_at": "2025-03-27T09:49:55.623841857Z",
      "issued_at": "2025-04-03T09:49:55.623841857Z",
      "grade": "C+",
      "credits": 4,
      "instructor": "Prof. Harris"
    },
    {
      "issuer_id": "IU-CS",
      "student_id": "ITITIU00033",
      "term_id": "Semester_2_2024",
      "course_id": "PH014IU",
      "course_name": "Physics 2",
      "attempt_no": 1,
      "started_at": "2025-01-19T23:35:24.11479694Z",
      "completed_at": "2025-03-21T07:24:46.173161055Z",
      "assessed_at": "2025-03-26T07:24:46.173161055Z",
      "issued_at": "2025-04-02T07:24:46.173161055Z",
      "grade": "D+",
      "credits": 2,
      "instructor": "Prof. Wilson"
    }
  ],
  "root": [
    138,
    85,
    92,
    75,
    252,
    185,
    229,
    239,
    221,
    54,
    83,
    166,
    1,
    243,
    39,
    89,
    179,
    216,
    53,
    6,
    5,
    93,
    113,
    138,
    106,
    162,
    213,
    145,
    78,
    187,
    189,
    215
  ],
  "leaves": [
    {
      "course": {
        "issuer_id": "IU-CHEM",
        "student_id": "ITITIU00033",
        "term_id": "Semester_2_2024",
        "course_id": "CH011IU",
        "course_name": "Chemistry for Engineers",
        "attempt_no": 1,
        "started_at": "2025-01-28T16:30:20.096317361Z",
        "completed_at": "2025-03-29T10:33:10.069927988Z",
        "assessed_at": "2025-04-01T10:33:10.069927988Z",
        "issued_at": "2025-04-15T10:33:10.069927988Z",
        "grade": "C+",
        "credits": 3,
        "instructor": "Prof. Davis"
      },
      "timestamp32": [
        0,
        0,
        0,
        0,
        103,
        153,
        6,
        28,
        0,
        0,
        0,
        0,
        103,
        231,
        204,
        102,
        0,
        0,
        0,
        0,
        103,
        235,
        192,
        230,
        0,
        0,
        0,
        0,
        103,
        254,
        53,
        230
      ],
      "course_hash32": [
        51,
        47,
        227,
        218,
        230,
        255,
        230,
        36,
        245,
        225,
        69,
        241,
        29,
        154,
        47,
        204,
        181,
        154,
        159,
        157,
        12,
        128,
        154,
        43,
        233,
        125,
        128,
        196,
        180,
        33,
        90,
        163
      ]
    },
    {
      "course": {
        "issuer_id": "IU-CS",
        "student_id": "ITITIU00033",
        "term_id": "Semester_2_2024",
        "course_id": "MA001IU",
        "course_name": "Calculus 1",
        "attempt_no": 1,
        "started_at": "2025-01-16T14:04:54.316561317Z",
        "completed_at": "2025-03-26T09:49:55.623841857Z",
        "assessed_at": "2025-03-27T09:49:55.623841857Z",
        "issued_at": "2025-04-03T09:49:55.623841857Z",
        "grade": "C+",
        "credits": 4,
        "instructor": "Prof. Harris"
      },
      "timestamp32": [
        0,
        0,
        0,
        0,
        103,
        137,
        18,
        6,
        0,
        0,
        0,
        0,
        103,
        227,
        205,
        195,
        0,
        0,
        0,
        0,
        103,
        229,
        31,
        67,
        0,
        0,
        0,
        0,
        103,
        238,
        89,
        195
      ],
      "course_hash32": [
        83,
        109,
        1,
        28,
        227,
        234,
        48,
        145,
        209,
        80,
        213,
        181,
        219,
        75,
        102,
        107,
        142,
        147,
        26,
        78,
        196,
        200,
        6,
        26,
        181,
        233,
        30,
        122,
        51,
        50,
        139,
        69
      ]
    },
    {
      "course": {
        "issuer_id": "IU-CS",
        "student_id": "ITITIU00033",
        "term_id": "Semester_2_2024",
        "course_id": "PH014IU",
        "course_name": "Physics 2",
        "attempt_no": 1,
        "started_at": "2025-01-19T23:35:24.11479694Z",
        "completed_at": "2025-03-21T07:24:46.173161055Z",
        "assessed_at": "2025-03-26T07:24:46.173161055Z",
        "issued_at": "2025-04-02T07:24:46.173161055Z",
        "grade": "D+",
        "credits": 2,
        "instructor": "Prof. Wilson"
      },
      "timestamp32": [
        0,
        0,
        0,
        0,
        103,
        141,
        140,
        60,
        0,
        0,
        0,
        0,
        103,
        221,
        20,
        62,
        0,
        0,
        0,
        0,
        103,
        227,
        171,
        190,
        0,
        0,
        0,
        0,
        103,
        236,
        230,
        62
      ],
      "course_hash32": [
        104,
        19,
        145,
        40,
        141,
        48,
        33,
        48,
        240,
        115,
        97,
        114,
        245,
        82,
        95,
        239,
        111,
        233,
        238,
        110,
        99,
        186,
        28,
        161,
        43,
        21,
        96,
        54,
        191,
        180,
        167,
        52
      ]
    }
  ],
  "proofs": {
    "CH011IU": [
      "cb7072ed0f2259be291698e65d47b322fb3a762651656a008791da3dd35ec1d4",
      "5d86f72709da9ea90170e65f290d4172b2d03bdf8827f06eaa8a51d48b0a2817"
    ],
    "MA001IU": [
      "c1cc77e3b25fbe7a06c31316c2a572a2a8458163d4b39a7d37e174b61a68b6bb",
      "5d86f72709da9ea90170e65f290d4172b2d03bdf8827f06eaa8a51d48b0a2817"
    ],
    "PH014IU": [
      "c9d732f99f00d136053a3821d4c76666af3298560fb1f810c722f51a01525dd5",
      "01ec3c9b7db57443d3a17338f79251319170b62dcea2efb0566eab478f2c5c9d"
    ]
  }
}