{
  "student_id": "did:example:ITITIU00047",
  "term_id": "Summer_2023",
  "courses": [
    {
      "issuer_id": "IU-CS",
      "student_id": "ITITIU00047",
      "term_id": "Summer_2023",
      "course_id": "IT133IU",
      "course_name": "Mobile Application Development",
      "attempt_no": 1,
      "started_at": "2023-06-11T11:38:13.408865797Z",
      "completed_at": "2023-06-30T17:55:53.502070484Z",
      "assessed_at": "2023-07-01T17:55:53.502070484Z",
      "issued_at": "2023-07-11T17:55:53.502070484Z",
      "grade": "C",
      "credits": 4,
      "instructor": "Prof. Miller"
    },
    {
      "issuer_id": "IU-PHYS",
      "student_id": "ITITIU00047",
      "term_id": "Summer_2023",
      "course_id": "MA001IU",
      "course_name": "Calculus 1",
      "attempt_no": 1,
      "started_at": "2023-06-10T15:12:08.096688434Z",
      "completed_at": "2023-06-27T09:20:10.388086052Z",
      "assessed_at": "2023-07-03T09:20:10.388086052Z",
      "issued_at": "2023-07-08T09:20:10.388086052Z",
      "grade": "B-",
      "credits": 4,
      "instructor": "Prof. Harris"
    },
    {
      "issuer_id": "IU-CS",
      "student_id": "ITITIU00047",
      "term_id": "Summer_2023",
      "course_id": "MA003IU",
      "course_name": "Calculus 2",
      "attempt_no": 1,
      "started_at": "2023-06-09T07:41:44.070347906Z",
      "completed_at": "2023-06-27T17:57:08.870946287Z",
      "assessed_at": "2023-07-02T17:57:08.870946287Z",
      "issued_at": "2023-07-13T17:57:08.870946287Z",
      "grade": "C",
      "credits": 4,
      "instructor": "Prof. Thomas"
    },
    {
      "issuer_id": "IU-CHEM",
      "student_id": "ITITIU00047",
      "term_id": "Summer_2023",
      "course_id": "MA026IU",
      "course_name": "Probability, Statistic \u0026 Random Process",
      "attempt_no": 1,
      "started_at": "2023-06-07T16:58:49.858450025Z",
      "completed_at": "2023-06-28T22:13:30.10622388Z",
      "assessed_at": "2023-07-02T22:13:30.10622388Z",
      "issued_at": "2023-07-06T22:13:30.10622388Z",
      "grade": "C",
      "credits": 3,
      "instructor": "Prof. Wilson"
    },
    {
      "issuer_id": "IU-PHYS",
      "student_id": "ITITIU00047",
      "term_id": "Summer_2023",
      "course_id": "PH015IU",
      "course_name": "Physics 3",
      "attempt_no": 1,
      "started_at": "2023-06-08T00:59:53.191350511Z",
      "completed_at": "2023-06-25T04:00:56.123998549Z",
      "assessed_at": "2023-06-28T04:00:56.123998549Z",
      "issued_at": "2023-07-03T04:00:56.123998549Z",
      "grade": "A",
      "credits": 3,
      "instructor": "Prof. Wilson"
    }
  ],
  "root": [
    7,
    22,
    48,
    135,
    198,
    87,
    209,
    45,
    71,
    35,
    70,
    252,
    173,
    69,
    62,
    6,
    226,
    198,
    212,
    170,
    112,
    42,
    122,
    147,
    39,
    126,
    227,
    38,
    216,
    195,
    27,
    74
  ],
  "leaves": [
    {
      "course": {
        "issuer_id": "IU-CS",
        "student_id": "ITITIU00047",
        "term_id": "Summer_2023",
        "course_id": "IT133IU",
        "course_name": "Mobile Application Development",
        "attempt_no": 1,
        "started_at": "2023-06-11T11:38:13.408865797Z",
        "completed_at": "2023-06-30T17:55:53.502070484Z",
        "assessed_at": "2023-07-01T17:55:53.502070484Z",
        "issued_at": "2023-07-11T17:55:53.502070484Z",
        "grade": "C",
        "credits": 4,
        "instructor": "Prof. Miller"
      },
      "timestamp32": [
        0,
        0,
        0,
        0,
        100,
        133,
        178,
        37,
        0,
        0,
        0,
        0,
        100,
        159,
        23,
        41,
        0,
        0,
        0,
        0,
        100,
        160,
        104,
        169,
        0,
        0,
        0,
        0,
        100,
        173,
        151,
        169
      ],
      "course_hash32": [
        211,
        212,
        232,
        231,
        62,
        205,
        23,
        28,
        216,
        141,
        12,
        163,
        71,
        5,
        173,
        202,
        195,
        65,
        58,
        183,
        14,
        105,
        182,
        192,
        204,
        39,
        133,
        198,
        162,
        156,
        252,
        237
      ]
    },
    {
      "course": {
        "issuer_id": "IU-PHYS",
        "student_id": "ITITIU00047",
        "term_id": "Summer_2023",
        "course_id": "MA001IU",
        "course_name": "Calculus 1",
        "attempt_no": 1,
        "started_at": "2023-06-10T15:12:08.096688434Z",
        "completed_at": "2023-06-27T09:20:10.388086052Z",
        "assessed_at": "2023-07-03T09:20:10.388086052Z",
        "issued_at": "2023-07-08T09:20:10.388086052Z",
        "grade": "B-",
        "credits": 4,
        "instructor": "Prof. Harris"
      },
      "timestamp32": [
        0,
        0,
        0,
        0,
        100,
        132,
        146,
        200,
        0,
        0,
        0,
        0,
        100,
        154,
        169,
        202,
        0,
        0,
        0,
        0,
        100,
        162,
        146,
        202,
        0,
        0,
        0,
        0,
        100,
        169,
        42,
        74
      ],
      "course_hash32": [
        102,
        113,
        30,
        249,
        112,
        83,
        21,
        232,
        24,
        121,
        201,
        161,
        217,
        26,
        56,
        117,
        136,
        220,
        168,
        189,
        84,
        187,
        123,
        103,
        247,
        212,
        245,
        190,
        33,
        138,
        56,
        201
      ]
    },
    {
      "course": {
        "issuer_id": "IU-CS",
        "student_id": "ITITIU00047",
        "term_id": "Summer_2023",
        "course_id": "MA003IU",
        "course_name": "Calculus 2",
        "attempt_no": 1,
        "started_at": "2023-06-09T07:41:44.070347906Z",
        "completed_at": "2023-06-27T17:57:08.870946287Z",
        "assessed_at": "2023-07-02T17:57:08.870946287Z",
        "issued_at": "2023-07-13T17:57:08.870946287Z",
        "grade": "C",
        "credits": 4,
        "instructor": "Prof. Thomas"
      },
      "timestamp32": [
        0,
        0,
        0,
        0,
        100,
        130,
        215,
        184,
        0,
        0,
        0,
        0,
        100,
        155,
        34,
        244,
        0,
        0,
        0,
        0,
        100,
        161,
        186,
        116,
        0,
        0,
        0,
        0,
        100,
        176,
        58,
        244
      ],
      "course_hash32": [
        67,
        11,
        210,
        126,
        37,
        195,
        122,
        133,
        36,
        189,
        18,
        58,
        221,
        225,
        14,
        103,
        96,
        8,
        175,
        68,
        83,
        11,
        21,
        30,
        130,
        173,
        88,
        205,
        110,
        24,
        57,
        22
      ]
    },
    {
      "course": {
        "issuer_id": "IU-CHEM",
        "student_id": "ITITIU00047",
        "term_id": "Summer_2023",
        "course_id": "MA026IU",
        "course_name": "Probability, Statistic \u0026 Random Process",
        "attempt_no": 1,
        "started_at": "2023-06-07T16:58:49.858450025Z",
        "completed_at": "2023-06-28T22:13:30.10622388Z",
        "assessed_at": "2023-07-02T22:13:30.10622388Z",
        "issued_at": "2023-07-06T22:13:30.10622388Z",
        "grade": "C",
        "credits": 3,
        "instructor": "Prof. Wilson"
      },
      "timestamp32": [
        0,
        0,
        0,
        0,
        100,
        128,
        183,
        73,
        0,
        0,
        0,
        0,
        100,
        156,
        176,
        138,
        0,
        0,
        0,
        0,
        100,
        161,
        246,
        138,
        0,
        0,
        0,
        0,
        100,
        167,
        60,
        138
      ],
      "course_hash32": [
        211,
        183,
        67,
        147,
        39,
        187,
        133,
        202,
        160,
        230,
        176,
        25,
        216,
        155,
        142,
        166,
        181,
        58,
        153,
        174,
        212,
        156,
        200,
        10,
        109,
        176,
        102,
        8,
        211,
        127,
        48,
        99
      ]
    },
    {
      "course": {
        "issuer_id": "IU-PHYS",
        "student_id": "ITITIU00047",
        "term_id": "Summer_2023",
        "course_id": "PH015IU",
        "course_name": "Physics 3",
        "attempt_no": 1,
        "started_at": "2023-06-08T00:59:53.191350511Z",
        "completed_at": "2023-06-25T04:00:56.123998549Z",
        "assessed_at": "2023-06-28T04:00:56.123998549Z",
        "issued_at": "2023-07-03T04:00:56.123998549Z",
        "grade": "A",
        "credits": 3,
        "instructor": "Prof. Wilson"
      },
      "timestamp32": [
        0,
        0,
        0,
        0,
        100,
        129,
        40,
        9,
        0,
        0,
        0,
        0,
        100,
        151,
        187,
        248,
        0,
        0,
        0,
        0,
        100,
        155,
        176,
        120,
        0,
        0,
        0,
        0,
        100,
        162,
        71,
        248
      ],
      "course_hash32": [
        66,
        29,
        108,
        66,
        198,
        61,
        163,
        167,
        184,
        4,
        224,
        39,
        65,
        57,
        154,
        242,
        54,
        46,
        93,
        8,
        120,
        130,
        128,
        33,
        226,
        152,
        21,
        38,
        108,
        70,
        171,
        72
      ]
    }
  ],
  "proofs": {
    "IT133IU": [
      "f618ee2f31eb0954b580b49aaa6cec9fa19bcc03b8b4eb3515d8dd3ae60a8905",
      "33cc4d26f1cbb987f959478b4735e4b097b2ca2668d709475a39894953af65e7",
      "f99250fb05e39337e39356e957523455de181bc1581a9549d059fa715f0e0338"
    ],
    "MA001IU": [
      "4aabc187c9fd12f82764caa566be2df8e939464e1dbf1b14890a5c3402e42692",
      "33cc4d26f1cbb987f959478b4735e4b097b2ca2668d709475a39894953af65e7",
      "f99250fb05e39337e39356e957523455de181bc1581a9549d059fa715f0e0338"
    ],
    "MA003IU": [
      "3547a77b1cbfa98996bdf4c7c176ea2e0b94088afb66a8a3fa44d5a43764d5ec",
      "339113392d1b164e1438e1b4ce7a35ca8d4002d4dd4ae2026c32477e21a129a0",
      "f99250fb05e39337e39356e957523455de181bc1581a9549d059fa715f0e0338"
    ],
    "MA026IU": [
      "f4b300af58eaf12ceee3161c9ff3452fc2977f40615f3c523dbc0a5270111110",
      "339113392d1b164e1438e1b4ce7a35ca8d4002d4dd4ae2026c32477e21a129a0",
      "f99250fb05e39337e39356e957523455de181bc1581a9549d059fa715f0e0338"
    ],
    "PH015IU": [
      "cc33ae0178fd90aa9cf4fabc850fbb3e7c0eac6e332c8529b6bcd3f5e16c0a27",
      "0d702b5ae1baeef0092f1a240febc09bda8e0da3a4eeb75534ca14c6546950ac",
      "50e7cf2f4c87c7f5d89c7fd46049c1bf697634ef12ac5e6c1b8e93680514ce83"
    ]
  }
}