{
  "student_id": "did:example:ITITIU00059",
  "term_id": "Summer_2023",
  "courses": [
    {
      "issuer_id": "IU-MATH",
      "student_id": "ITITIU00059",
      "term_id": "Summer_2023",
      "course_id": "CH011IU",
      "course_name": "Chemistry for Engineers",
      "attempt_no": 1,
      "started_at": "2023-06-04T11:52:38.793007052Z",
      "completed_at": "2023-06-29T03:32:36.491361598Z",
      "assessed_at": "2023-07-01T03:32:36.491361598Z",
      "issued_at": "2023-07-05T03:32:36.491361598Z",
      "grade": "D+",
      "credits": 3,
      "instructor": "Prof. Thomas"
    },
    {
      "issuer_id": "IU-PHYS",
      "student_id": "ITITIU00059",
      "term_id": "Summer_2023",
      "course_id": "IT089IU",
      "course_name": "Computer Architecture",
      "attempt_no": 1,
      "started_at": "2023-06-04T05:33:22.321772115Z",
      "completed_at": "2023-06-25T01:30:43.458782104Z",
      "assessed_at": "2023-06-26T01:30:43.458782104Z",
      "issued_at": "2023-07-09T01:30:43.458782104Z",
      "grade": "D",
      "credits": 4,
      "instructor": "Prof. Jackson"
    },
    {
      "issuer_id": "IU-PHYS",
      "student_id": "ITITIU00059",
      "term_id": "Summer_2023",
      "course_id": "IT116IU",
      "course_name": "C/C++ Programming",
      "attempt_no": 1,
      "started_at": "2023-06-08T16:35:00.703136157Z",
      "completed_at": "2023-06-25T16:06:00.056616885Z",
      "assessed_at": "2023-07-01T16:06:00.056616885Z",
      "issued_at": "2023-07-02T16:06:00.056616885Z",
      "grade": "C+",
      "credits": 4,
      "instructor": "Prof. Smith"
    },
    {
      "issuer_id": "IU-CHEM",
      "student_id": "ITITIU00059",
      "term_id": "Summer_2023",
      "course_id": "IT154IU",
      "course_name": "Linear Algebra",
      "attempt_no": 1,
      "started_at": "2023-06-02T18:46:21.661461468Z",
      "completed_at": "2023-07-02T16:38:27.352122797Z",
      "assessed_at": "2023-07-05T16:38:27.352122797Z",
      "issued_at": "2023-07-14T16:38:27.352122797Z",
      "grade": "B",
      "credits": 3,
      "instructor": "Prof. Wilson"
    },
    {
      "issuer_id": "IU-CS",
      "student_id": "ITITIU00059",
      "term_id": "Summer_2023",
      "course_id": "PH015IU",
      "course_name": "Physics 3",
      "attempt_no": 1,
      "started_at": "2023-06-10T07:23:37.773098958Z",
      "completed_at": "2023-06-30T10:17:17.439254114Z",
      "assessed_at": "2023-07-07T10:17:17.439254114Z",
      "issued_at": "2023-07-17T10:17:17.439254114Z",
      "grade": "A",
      "credits": 3,
      "instructor": "Prof. Jackson"
    }
  ],
  "root": [
    190,
    35,
    183,
    47,
    145,
    241,
    148,
    81,
    220,
    156,
    54,
    215,
    124,
    122,
    231,
    253,
    76,
    36,
    218,
    225,
    156,
    133,
    72,
    38,
    144,
    164,
    104,
    128,
    202,
    95,
    1,
    186
  ],
  "leaves": [
    {
      "course": {
        "issuer_id": "IU-MATH",
        "student_id": "ITITIU00059",
        "term_id": "Summer_2023",
        "course_id": "CH011IU",
        "course_name": "Chemistry for Engineers",
        "attempt_no": 1,
        "started_at": "2023-06-04T11:52:38.793007052Z",
        "completed_at": "2023-06-29T03:32:36.491361598Z",
        "assessed_at": "2023-07-01T03:32:36.491361598Z",
        "issued_at": "2023-07-05T03:32:36.491361598Z",
        "grade": "D+",
        "credits": 3,
        "instructor": "Prof. Thomas"
      },
      "timestamp32": [
        0,
        0,
        0,
        0,
        100,
        124,
        123,
        6,
        0,
        0,
        0,
        0,
        100,
        156,
        251,
        84,
        0,
        0,
        0,
        0,
        100,
        159,
        158,
        84,
        0,
        0,
        0,
        0,
        100,
        164,
        228,
        84
      ],
      "course_hash32": [
        24,
        243,
        11,
        26,
        41,
        185,
        176,
        30,
        46,
        136,
        249,
        27,
        124,
        155,
        21,
        108,
        160,
        123,
        173,
        21,
        182,
        30,
        46,
        97,
        84,
        42,
        35,
        221,
        81,
        60,
        197,
        101
      ]
    },
    {
      "course": {
        "issuer_id": "IU-PHYS",
        "student_id": "ITITIU00059",
        "term_id": "Summer_2023",
        "course_id": "IT089IU",
        "course_name": "Computer Architecture",
        "attempt_no": 1,
        "started_at": "2023-06-04T05:33:22.321772115Z",
        "completed_at": "2023-06-25T01:30:43.458782104Z",
        "assessed_at": "2023-06-26T01:30:43.458782104Z",
        "issued_at": "2023-07-09T01:30:43.458782104Z",
        "grade": "D",
        "credits": 4,
        "instructor": "Prof. Jackson"
      },
      "timestamp32": [
        0,
        0,
        0,
        0,
        100,
        124,
        34,
        34,
        0,
        0,
        0,
        0,
        100,
        151,
        152,
        195,
        0,
        0,
        0,
        0,
        100,
        152,
        234,
        67,
        0,
        0,
        0,
        0,
        100,
        170,
        13,
        195
      ],
      "course_hash32": [
        168,
        224,
        150,
        28,
        224,
        175,
        194,
        231,
        110,
        40,
        215,
        234,
        173,
        126,
        42,
        57,
        207,
        96,
        147,
        199,
        143,
        89,
        180,
        93,
        201,
        75,
        127,
        98,
        217,
        193,
        251,
        233
      ]
    },
    {
      "course": {
        "issuer_id": "IU-PHYS",
        "student_id": "ITITIU00059",
        "term_id": "Summer_2023",
        "course_id": "IT116IU",
        "course_name": "C/C++ Programming",
        "attempt_no": 1,
        "started_at": "2023-06-08T16:35:00.703136157Z",
        "completed_at": "2023-06-25T16:06:00.056616885Z",
        "assessed_at": "2023-07-01T16:06:00.056616885Z",
        "issued_at": "2023-07-02T16:06:00.056616885Z",
        "grade": "C+",
        "credits": 4,
        "instructor": "Prof. Smith"
      },
      "timestamp32": [
        0,
        0,
        0,
        0,
        100,
        130,
        3,
        52,
        0,
        0,
        0,
        0,
        100,
        152,
        101,
        232,
        0,
        0,
        0,
        0,
        100,
        160,
        78,
        232,
        0,
        0,
        0,
        0,
        100,
        161,
        160,
        104
      ],
      "course_hash32": [
        229,
        94,
        60,
        251,
        137,
        68,
        89,
        30,
        58,
        254,
        3,
        91,
        1,
        231,
        236,
        127,
        146,
        207,
        143,
        195,
        39,
        132,
        242,
        180,
        3,
        46,
        122,
        128,
        30,
        148,
        214,
        101
      ]
    },
    {
      "course": {
        "issuer_id": "IU-CHEM",
        "student_id": "ITITIU00059",
        "term_id": "Summer_2023",
        "course_id": "IT154IU",
        "course_name": "Linear Algebra",
        "attempt_no": 1,
        "started_at": "2023-06-02T18:46:21.661461468Z",
        "completed_at": "2023-07-02T16:38:27.352122797Z",
        "assessed_at": "2023-07-05T16:38:27.352122797Z",
        "issued_at": "2023-07-14T16:38:27.352122797Z",
        "grade": "B",
        "credits": 3,
        "instructor": "Prof. Wilson"
      },
      "timestamp32": [
        0,
        0,
        0,
        0,
        100,
        122,
        56,
        253,
        0,
        0,
        0,
        0,
        100,
        161,
        168,
        3,
        0,
        0,
        0,
        0,
        100,
        165,
        156,
        131,
        0,
        0,
        0,
        0,
        100,
        177,
        122,
        3
      ],
      "course_hash32": [
        241,
        209,
        4,
        179,
        85,
        8,
        33,
        203,
        81,
        141,
        152,
        136,
        147,
        186,
        244,
        186,
        15,
        29,
        150,
        42,
        199,
        74,
        176,
        222,
        200,
        4,
        56,
        185,
        191,
        98,
        232,
        21
      ]
    },
    {
      "course": {
        "issuer_id": "IU-CS",
        "student_id": "ITITIU00059",
        "term_id": "Summer_2023",
        "course_id": "PH015IU",
        "course_name": "Physics 3",
        "attempt_no": 1,
        "started_at": "2023-06-10T07:23:37.773098958Z",
        "completed_at": "2023-06-30T10:17:17.439254114Z",
        "assessed_at": "2023-07-07T10:17:17.439254114Z",
        "issued_at": "2023-07-17T10:17:17.439254114Z",
        "grade": "A",
        "credits": 3,
        "instructor": "Prof. Jackson"
      },
      "timestamp32": [
        0,
        0,
        0,
        0,
        100,
        132,
        36,
        249,
        0,
        0,
        0,
        0,
        100,
        158,
        171,
        173,
        0,
        0,
        0,
        0,
        100,
        167,
        230,
        45,
        0,
        0,
        0,
        0,
        100,
        181,
        21,
        45
      ],
      "course_hash32": [
        152,
        231,
        240,
        125,
        55,
        141,
        72,
        196,
        40,
        209,
        9,
        65,
        183,
        226,
        220,
        204,
        241,
        50,
        3,
        137,
        239,
        148,
        55,
        231,
        75,
        203,
        36,
        23,
        37,
        215,
        50,
        94
      ]
    }
  ],
  "proofs": {
    "CH011IU": [
      "858be2e82e30f8218b58ab2d49804cffb10d3da49d856b948c850b0b728697d6",
      "1773f9046f5c23aae4c336ac00da7e59565ba76b260cdfca2938d75cc3dd8921",
      "693ff2d2cba10cbf6943013ce66344debf806edee3447b101bc76edbe322c639"
    ],
    "IT089IU": [
      "7c880a6d9c7e515b007c0252685288e80187bcb41e2ff013aea0ec9151ceaa8d",
      "1773f9046f5c23aae4c336ac00da7e59565ba76b260cdfca2938d75cc3dd8921",
      "693ff2d2cba10cbf6943013ce66344debf806edee3447b101bc76edbe322c639"
    ],
    "IT116IU": [
      "6a6951d409ccf5ec766f2473b0d13d7a1da2a5125198c412f1c3179b62a666e3",
      "e66a2e4428b448b6f85eb2707ff0d48ac4c7e21810ca809a2573ad6c63ef47bb",
      "693ff2d2cba10cbf6943013ce66344debf806edee3447b101bc76edbe322c639"
    ],
    "IT154IU": [
      "0f67b6bf9c139ac14cd7ec9775ef6c28c3588007403beb7fcd2b9ec836771651",
      "e66a2e4428b448b6f85eb2707ff0d48ac4c7e21810ca809a2573ad6c63ef47bb",
      "693ff2d2cba10cbf6943013ce66344debf806edee3447b101bc76edbe322c639"
    ],
    "PH015IU": [
      "48f75964676246f1a830df7c76fb97e5e77fb4d7f23e325a2210872683e0ec6b",
      "2be53f45c773f30457b7020df72fe80187618b5f86661ae2e42932ffc97aed9b",
      "989f1728e7eec24eeefedb1495f9b9e42b770355ba5b77adf6e1c785bc2aed9c"
    ]
  }
}