{
  "student_id": "did:example:ITITIU00007",
  "term_id": "Semester_1_2023",
  "courses": [
    {
      "issuer_id": "IU-PHYS",
      "student_id": "ITITIU00007",
      "term_id": "Semester_1_2023",
      "course_id": "CH011IU",
      "course_name": "Chemistry for Engineers",
      "attempt_no": 1,
      "started_at": "2023-08-22T13:25:33.130651686Z",
      "completed_at": "2023-11-08T04:16:17.190587328Z",
      "assessed_at": "2023-11-12T04:16:17.190587328Z",
      "issued_at": "2023-11-18T04:16:17.190587328Z",
      "grade": "C-",
      "credits": 3,
      "instructor": "Prof. White"
    },
    {
      "issuer_id": "IU-MATH",
      "student_id": "ITITIU00007",
      "term_id": "Semester_1_2023",
      "course_id": "IT091IU",
      "course_name": "Computer Networks",
      "attempt_no": 1,
      "started_at": "2023-09-09T04:52:23.434034252Z",
      "completed_at": "2023-11-04T06:32:50.054182763Z",
      "assessed_at": "2023-11-06T06:32:50.054182763Z",
      "issued_at": "2023-11-15T06:32:50.054182763Z",
      "grade": "A",
      "credits": 4,
      "instructor": "Prof. Brown"
    },
    {
      "issuer_id": "IU-CS",
      "student_id": "ITITIU00007",
      "term_id": "Semester_1_2023",
      "course_id": "IT134IU",
      "course_name": "Internet of Things",
      "attempt_no": 1,
      "started_at": "2023-08-18T00:31:42.356325654Z",
      "completed_at": "2023-10-21T05:10:40.52699537Z",
      "assessed_at": "2023-10-27T05:10:40.52699537Z",
      "issued_at": "2023-11-10T05:10:40.52699537Z",
      "grade": "A-",
      "credits": 4,
      "instructor": "Prof. Brown"
    },
    {
      "issuer_id": "IU-PHYS",
      "student_id": "ITITIU00007",
      "term_id": "Semester_1_2023",
      "course_id": "IT160IU",
      "course_name": "Data Mining",
      "attempt_no": 1,
      "started_at": "2023-09-08T16:01:22.884961936Z",
      "completed_at": "2023-11-03T17:48:31.847192511Z",
      "assessed_at": "2023-11-05T17:48:31.847192511Z",
      "issued_at": "2023-11-06T17:48:31.847192511Z",
      "grade": "D",
      "credits": 4,
      "instructor": "Prof. White"
    },
    {
      "issuer_id": "IU-BUS",
      "student_id": "ITITIU00007",
      "term_id": "Semester_1_2023",
      "course_id": "PE008IU",
      "course_name": "Critical Thinking",
      "attempt_no": 1,
      "started_at": "2023-08-17T07:46:31.665326647Z",
      "completed_at": "2023-10-29T06:40:39.215472858Z",
      "assessed_at": "2023-11-02T06:40:39.215472858Z",
      "issued_at": "2023-11-16T06:40:39.215472858Z",
      "grade": "C+",
      "credits": 3,
      "instructor": "Prof. White"
    }
  ],
  "root": [
    133,
    28,
    253,
    184,
    93,
    79,
    138,
    195,
    235,
    42,
    244,
    184,
    111,
    146,
    223,
    142,
    169,
    129,
    61,
    146,
    250,
    74,
    36,
    27,
    18,
    227,
    9,
    116,
    108,
    61,
    107,
    223
  ],
  "leaves": [
    {
      "course": {
        "issuer_id": "IU-PHYS",
        "student_id": "ITITIU00007",
        "term_id": "Semester_1_2023",
        "course_id": "CH011IU",
        "course_name": "Chemistry for Engineers",
        "attempt_no": 1,
        "started_at": "2023-08-22T13:25:33.130651686Z",
        "completed_at": "2023-11-08T04:16:17.190587328Z",
        "assessed_at": "2023-11-12T04:16:17.190587328Z",
        "issued_at": "2023-11-18T04:16:17.190587328Z",
        "grade": "C-",
        "credits": 3,
        "instructor": "Prof. White"
      },
      "timestamp32": [
        0,
        0,
        0,
        0,
        100,
        228,
        183,
        77,
        0,
        0,
        0,
        0,
        101,
        75,
        11,
        145,
        0,
        0,
        0,
        0,
        101,
        80,
        81,
        145,
        0,
        0,
        0,
        0,
        101,
        88,
        58,
        145
      ],
      "course_hash32": [
        21,
        56,
        169,
        148,
        151,
        93,
        253,
        200,
        230,
        77,
        109,
        216,
        28,
        111,
        2,
        6,
        180,
        77,
        74,
        41,
        93,
        213,
        167,
        117,
        132,
        76,
        21,
        147,
        241,
        23,
        36,
        226
      ]
    },
    {
      "course": {
        "issuer_id": "IU-MATH",
        "student_id": "ITITIU00007",
        "term_id": "Semester_1_2023",
        "course_id": "IT091IU",
        "course_name": "Computer Networks",
        "attempt_no": 1,
        "started_at": "2023-09-09T04:52:23.434034252Z",
        "completed_at": "2023-11-04T06:32:50.054182763Z",
        "assessed_at": "2023-11-06T06:32:50.054182763Z",
        "issued_at": "2023-11-15T06:32:50.054182763Z",
        "grade": "A",
        "credits": 4,
        "instructor": "Prof. Brown"
      },
      "timestamp32": [
        0,
        0,
        0,
        0,
        100,
        251,
        250,
        7,
        0,
        0,
        0,
        0,
        101,
        69,
        229,
        146,
        0,
        0,
        0,
        0,
        101,
        72,
        136,
        146,
        0,
        0,
        0,
        0,
        101,
        84,
        102,
        18
      ],
      "course_hash32": [
        46,
        247,
        68,
        198,
        207,
        138,
        173,
        197,
        115,
        184,
        46,
        253,
        149,
        56,
        103,
        13,
        241,
        194,
        218,
        100,
        8,
        48,
        223,
        21,
        163,
        61,
        129,
        176,
        40,
        104,
        165,
        21
      ]
    },
    {
      "course": {
        "issuer_id": "IU-CS",
        "student_id": "ITITIU00007",
        "term_id": "Semester_1_2023",
        "course_id": "IT134IU",
        "course_name": "Internet of Things",
        "attempt_no": 1,
        "started_at": "2023-08-18T00:31:42.356325654Z",
        "completed_at": "2023-10-21T05:10:40.52699537Z",
        "assessed_at": "2023-10-27T05:10:40.52699537Z",
        "issued_at": "2023-11-10T05:10:40.52699537Z",
        "grade": "A-",
        "credits": 4,
        "instructor": "Prof. Brown"
      },
      "timestamp32": [
        0,
        0,
        0,
        0,
        100,
        222,
        187,
        238,
        0,
        0,
        0,
        0,
        101,
        51,
        93,
        80,
        0,
        0,
        0,
        0,
        101,
        59,
        70,
        80,
        0,
        0,
        0,
        0,
        101,
        77,
        187,
        80
      ],
      "course_hash32": [
        204,
        8,
        57,
        7,
        101,
        138,
        233,
        68,
        86,
        192,
        42,
        42,
        68,
        168,
        183,
        89,
        21,
        240,
        153,
        161,
        70,
        227,
        108,
        25,
        93,
        215,
        189,
        213,
        181,
        114,
        225,
        26
      ]
    },
    {
      "course": {
        "issuer_id": "IU-PHYS",
        "student_id": "ITITIU00007",
        "term_id": "Semester_1_2023",
        "course_id": "IT160IU",
        "course_name": "Data Mining",
        "attempt_no": 1,
        "started_at": "2023-09-08T16:01:22.884961936Z",
        "completed_at": "2023-11-03T17:48:31.847192511Z",
        "assessed_at": "2023-11-05T17:48:31.847192511Z",
        "issued_at": "2023-11-06T17:48:31.847192511Z",
        "grade": "D",
        "credits": 4,
        "instructor": "Prof. White"
      },
      "timestamp32": [
        0,
        0,
        0,
        0,
        100,
        251,
        69,
        82,
        0,
        0,
        0,
        0,
        101,
        69,
        50,
        111,
        0,
        0,
        0,
        0,
        101,
        71,
        213,
        111,
        0,
        0,
        0,
        0,
        101,
        73,
        38,
        239
      ],
      "course_hash32": [
        108,
        91,
        4,
        157,
        43,
        183,
        41,
        99,
        102,
        124,
        16,
        211,
        162,
        39,
        164,
        227,
        169,
        133,
        78,
        37,
        244,
        179,
        72,
        11,
        225,
        170,
        203,
        41,
        37,
        65,
        203,
        14
      ]
    },
    {
      "course": {
        "issuer_id": "IU-BUS",
        "student_id": "ITITIU00007",
        "term_id": "Semester_1_2023",
        "course_id": "PE008IU",
        "course_name": "Critical Thinking",
        "attempt_no": 1,
        "started_at": "2023-08-17T07:46:31.665326647Z",
        "completed_at": "2023-10-29T06:40:39.215472858Z",
        "assessed_at": "2023-11-02T06:40:39.215472858Z",
        "issued_at": "2023-11-16T06:40:39.215472858Z",
        "grade": "C+",
        "credits": 3,
        "instructor": "Prof. White"
      },
      "timestamp32": [
        0,
        0,
        0,
        0,
        100,
        221,
        208,
        87,
        0,
        0,
        0,
        0,
        101,
        61,
        254,
        103,
        0,
        0,
        0,
        0,
        101,
        67,
        68,
        103,
        0,
        0,
        0,
        0,
        101,
        85,
        185,
        103
      ],
      "course_hash32": [
        54,
        200,
        199,
        22,
        133,
        251,
        253,
        82,
        61,
        229,
        146,
        36,
        154,
        123,
        210,
        98,
        129,
        166,
        178,
        174,
        217,
        28,
        132,
        112,
        74,
        241,
        70,
        8,
        251,
        57,
        23,
        232
      ]
    }
  ],
  "proofs": {
    "CH011IU": [
      "1a55c4e544a18f0629486b21f2ab64b6e1cabe92ef46a3d6ffd1d4aa1fbf3d4c",
      "797f244f256513f971dd99c46e27094d7c55a46f1f589fe30360383134f648d5",
      "171fd885bbba2ade9c135cf125b7c2ce78c6d5f34398bfc91cadbdcc133b9160"
    ],
    "IT091IU": [
      "532141ace8c2fd3e15873dd538e6c24edab404b48d1b7bff5a0c8bf14455e681",
      "797f244f256513f971dd99c46e27094d7c55a46f1f589fe30360383134f648d5",
      "171fd885bbba2ade9c135cf125b7c2ce78c6d5f34398bfc91cadbdcc133b9160"
    ],
    "IT134IU": [
      "0195e617d9a44bb1c28d57e9094cdce3dfa9bb1ae99948720e482736c430cbbd",
      "b8cea802d4979972dedaf0f8668026cdf6edf21f35d0dbaf531a556cd8346401",
      "171fd885bbba2ade9c135cf125b7c2ce78c6d5f34398bfc91cadbdcc133b9160"
    ],
    "IT160IU": [
      "5273a33cbca252449f4fb7b93b589d67d2224a4a33247c13b1dcd4bcd22472c9",
      "b8cea802d4979972dedaf0f8668026cdf6edf21f35d0dbaf531a556cd8346401",
      "171fd885bbba2ade9c135cf125b7c2ce78c6d5f34398bfc91cadbdcc133b9160"
    ],
    "PE008IU": [
      "f29cbf25304be37195fc8c5670fc8c2fd6e1aaca946639118d2dbc1daca67fde",
      "1b02fa9f15c4549386281abb8d952a209cdee98db71fbdf3092824f8616809d6",
      "2e5ad3db7b556a3904dd85a0752c65a19f0dcb5d606b01037e089ed8587b81c1"
    ]
  }
}