{
  "student_id": "did:example:ITITIU00099",
  "term_id": "Semester_1_2023",
  "courses": [
    {
      "issuer_id": "IU-MATH",
      "student_id": "ITITIU00099",
      "term_id": "Semester_1_2023",
      "course_id": "IT013IU",
      "course_name": "Algorithms \u0026 Data Structures",
      "attempt_no": 1,
      "started_at": "2023-08-19T16:01:27.769046747Z",
      "completed_at": "2023-10-28T10:59:20.527413749Z",
      "assessed_at": "2023-10-31T10:59:20.527413749Z",
      "issued_at": "2023-11-05T10:59:20.527413749Z",
      "grade": "B-",
      "credits": 4,
      "instructor": "Prof. Thomas"
    },
    {
      "issuer_id": "IU-BUS",
      "student_id": "ITITIU00099",
      "term_id": "Semester_1_2023",
      "course_id": "IT013IU",
      "course_name": "Algorithms \u0026 Data Structures",
      "attempt_no": 1,
      "started_at": "2023-09-06T02:54:15.33841606Z",
      "completed_at": "2023-11-04T20:24:06.675039615Z",
      "assessed_at": "2023-11-11T20:24:06.675039615Z",
      "issued_at": "2023-11-14T20:24:06.675039615Z",
      "grade": "C+",
      "credits": 4,
      "instructor": "Prof. Miller"
    },
    {
      "issuer_id": "IU-MATH",
      "student_id": "ITITIU00099",
      "term_id": "Semester_1_2023",
      "course_id": "IT076IU",
      "course_name": "Software Engineering",
      "attempt_no": 1,
      "started_at": "2023-08-27T02:58:24.316169869Z",
      "completed_at": "2023-10-31T19:17:29.333541848Z",
      "assessed_at": "2023-11-06T19:17:29.333541848Z",
      "issued_at": "2023-11-11T19:17:29.333541848Z",
      "grade": "D+",
      "credits": 4,
      "instructor": "Prof. Smith"
    },
    {
      "issuer_id": "IU-CS",
      "student_id": "ITITIU00099",
      "term_id": "Semester_1_2023",
      "course_id": "IT091IU",
      "course_name": "Computer Networks",
      "attempt_no": 1,
      "started_at": "2023-08-29T22:04:32.897403701Z",
      "completed_at": "2023-11-01T08:05:44.479479138Z",
      "assessed_at": "2023-11-05T08:05:44.479479138Z",
      "issued_at": "2023-11-10T08:05:44.479479138Z",
      "grade": "B",
      "credits": 4,
      "instructor": "Prof. Harris"
    },
    {
      "issuer_id": "IU-CHEM",
      "student_id": "ITITIU00099",
      "term_id": "Semester_1_2023",
      "course_id": "PH015IU",
      "course_name": "Physics 3",
      "attempt_no": 1,
      "started_at": "2023-08-26T10:36:24.917142443Z",
      "completed_at": "2023-10-24T21:42:58.182692881Z",
      "assessed_at": "2023-10-25T21:42:58.182692881Z",
      "issued_at": "2023-10-26T21:42:58.182692881Z",
      "grade": "B+",
      "credits": 3,
      "instructor": "Prof. Smith"
    }
  ],
  "root": [
    76,
    60,
    175,
    202,
    53,
    68,
    155,
    167,
    44,
    166,
    120,
    114,
    2,
    223,
    182,
    37,
    244,
    227,
    38,
    134,
    91,
    87,
    82,
    125,
    243,
    120,
    20,
    6,
    103,
    118,
    189,
    107
  ],
  "leaves": [
    {
      "course": {
        "issuer_id": "IU-MATH",
        "student_id": "ITITIU00099",
        "term_id": "Semester_1_2023",
        "course_id": "IT013IU",
        "course_name": "Algorithms \u0026 Data Structures",
        "attempt_no": 1,
        "started_at": "2023-08-19T16:01:27.769046747Z",
        "completed_at": "2023-10-28T10:59:20.527413749Z",
        "assessed_at": "2023-10-31T10:59:20.527413749Z",
        "issued_at": "2023-11-05T10:59:20.527413749Z",
        "grade": "B-",
        "credits": 4,
        "instructor": "Prof. Thomas"
      },
      "timestamp32": [
        0,
        0,
        0,
        0,
        100,
        224,
        231,
        87,
        0,
        0,
        0,
        0,
        101,
        60,
        233,
        136,
        0,
        0,
        0,
        0,
        101,
        64,
        222,
        8,
        0,
        0,
        0,
        0,
        101,
        71,
        117,
        136
      ],
      "course_hash32": [
        50,
        251,
        26,
        75,
        165,
        142,
        178,
        1,
        167,
        249,
        233,
        129,
        161,
        133,
        145,
        253,
        141,
        16,
        45,
        241,
        170,
        170,
        160,
        60,
        54,
        62,
        34,
        215,
        65,
        99,
        39,
        165
      ]
    },
    {
      "course": {
        "issuer_id": "IU-BUS",
        "student_id": "ITITIU00099",
        "term_id": "Semester_1_2023",
        "course_id": "IT013IU",
        "course_name": "Algorithms \u0026 Data Structures",
        "attempt_no": 1,
        "started_at": "2023-09-06T02:54:15.33841606Z",
        "completed_at": "2023-11-04T20:24:06.675039615Z",
        "assessed_at": "2023-11-11T20:24:06.675039615Z",
        "issued_at": "2023-11-14T20:24:06.675039615Z",
        "grade": "C+",
        "credits": 4,
        "instructor": "Prof. Miller"
      },
      "timestamp32": [
        0,
        0,
        0,
        0,
        100,
        247,
        233,
        215,
        0,
        0,
        0,
        0,
        101,
        70,
        168,
        102,
        0,
        0,
        0,
        0,
        101,
        79,
        226,
        230,
        0,
        0,
        0,
        0,
        101,
        83,
        215,
        102
      ],
      "course_hash32": [
        156,
        90,
        237,
        1,
        76,
        206,
        84,
        74,
        197,
        207,
        210,
        17,
        82,
        9,
        84,
        40,
        139,
        215,
        196,
        123,
        70,
        72,
        109,
        13,
        102,
        96,
        25,
        79,
        222,
        90,
        133,
        144
      ]
    },
    {
      "course": {
        "issuer_id": "IU-MATH",
        "student_id": "ITITIU00099",
        "term_id": "Semester_1_2023",
        "course_id": "IT076IU",
        "course_name": "Software Engineering",
        "attempt_no": 1,
        "started_at": "2023-08-27T02:58:24.316169869Z",
        "completed_at": "2023-10-31T19:17:29.333541848Z",
        "assessed_at": "2023-11-06T19:17:29.333541848Z",
        "issued_at": "2023-11-11T19:17:29.333541848Z",
        "grade": "D+",
        "credits": 4,
        "instructor": "Prof. Smith"
      },
      "timestamp32": [
        0,
        0,
        0,
        0,
        100,
        234,
        187,
        208,
        0,
        0,
        0,
        0,
        101,
        65,
        82,
        201,
        0,
        0,
        0,
        0,
        101,
        73,
        59,
        201,
        0,
        0,
        0,
        0,
        101,
        79,
        211,
        73
      ],
      "course_hash32": [
        70,
        253,
        75,
        148,
        213,
        237,
        142,
        48,
        232,
        122,
        55,
        196,
        114,
        227,
        166,
        93,
        221,
        235,
        233,
        175,
        34,
        246,
        117,
        26,
        160,
        147,
        56,
        175,
        138,
        113,
        199,
        217
      ]
    },
    {
      "course": {
        "issuer_id": "IU-CS",
        "student_id": "ITITIU00099",
        "term_id": "Semester_1_2023",
        "course_id": "IT091IU",
        "course_name": "Computer Networks",
        "attempt_no": 1,
        "started_at": "2023-08-29T22:04:32.897403701Z",
        "completed_at": "2023-11-01T08:05:44.479479138Z",
        "assessed_at": "2023-11-05T08:05:44.479479138Z",
        "issued_at": "2023-11-10T08:05:44.479479138Z",
        "grade": "B",
        "credits": 4,
        "instructor": "Prof. Harris"
      },
      "timestamp32": [
        0,
        0,
        0,
        0,
        100,
        238,
        107,
        112,
        0,
        0,
        0,
        0,
        101,
        66,
        6,
        216,
        0,
        0,
        0,
        0,
        101,
        71,
        76,
        216,
        0,
        0,
        0,
        0,
        101,
        77,
        228,
        88
      ],
      "course_hash32": [
        126,
        42,
        64,
        183,
        110,
        156,
        128,
        207,
        69,
        192,
        88,
        206,
        70,
        148,
        12,
        151,
        209,
        96,
        203,
        123,
        239,
        255,
        122,
        55,
        149,
        10,
        201,
        139,
        56,
        180,
        195,
        172
      ]
    },
    {
      "course": {
        "issuer_id": "IU-CHEM",
        "student_id": "ITITIU00099",
        "term_id": "Semester_1_2023",
        "course_id": "PH015IU",
        "course_name": "Physics 3",
        "attempt_no": 1,
        "started_at": "2023-08-26T10:36:24.917142443Z",
        "completed_at": "2023-10-24T21:42:58.182692881Z",
        "assessed_at": "2023-10-25T21:42:58.182692881Z",
        "issued_at": "2023-10-26T21:42:58.182692881Z",
        "grade": "B+",
        "credits": 3,
        "instructor": "Prof. Smith"
      },
      "timestamp32": [
        0,
        0,
        0,
        0,
        100,
        233,
        213,
        168,
        0,
        0,
        0,
        0,
        101,
        56,
        58,
        98,
        0,
        0,
        0,
        0,
        101,
        57,
        139,
        226,
        0,
        0,
        0,
        0,
        101,
        58,
        221,
        98
      ],
      "course_hash32": [
        107,
        220,
        116,
        128,
        89,
        125,
        181,
        23,
        171,
        229,
        174,
        221,
        21,
        51,
        35,
        250,
        253,
        167,
        9,
        227,
        218,
        250,
        146,
        98,
        208,
        205,
        172,
        25,
        214,
        69,
        110,
        43
      ]
    }
  ],
  "proofs": {
    "IT013IU": [
      "25cb5b756c6bbea9c3b10dfde64db69a53de32cfe9a1df9e88d5f79aff6e0b5a",
      "16b8ba9be3f735b391e27d00b029561d0aca308fac44e229e20f4d874ea37981",
      "5e1f0c2ffac0d6f498b80985b908809355bcf5b23bc6cf631418a04d661daf63"
    ],
    "IT076IU": [
      "4744fb7b8673392d49152413f67f67c84ef1b7a6cdb20f46b3f0e2c5d1e0cc1b",
      "974c5614317b57178847113d4e152c937b0c1bf9b34c6363fc9e3afb21424229",
      "5e1f0c2ffac0d6f498b80985b908809355bcf5b23bc6cf631418a04d661daf63"
    ],
    "IT091IU": [
      "a865f3824135d413df4108972910ec25ac71ef3c780008ce3daf44361cf69971",
      "974c5614317b57178847113d4e152c937b0c1bf9b34c6363fc9e3afb21424229",
      "5e1f0c2ffac0d6f498b80985b908809355bcf5b23bc6cf631418a04d661daf63"
    ],
    "PH015IU": [
      "cefb046b3904ad58f7b64a2e40abd3573d838cc540e183327b8c60ac927892aa",
      "221e3dc9876840cd8e3634076b8becc9e55977ccf0b690d70657110be4ab78db",
      "16949546f6c070dbbfc1aea4e117077736fefe7129e4f3d38125e2f924e08d4b"
    ]
  }
}