{
  "student_id": "did:example:ITITIU00087",
  "terms": {
    "Semester_1_2023": {
      "courses": [
        {
          "assessed_at": "2023-10-29T23:12:03.06138606Z",
          "attempt_no": 1,
          "completed_at": "2023-10-28T23:12:03.06138606Z",
          "course_id": "IT089IU",
          "course_name": "Computer Architecture",
          "credits": 4,
          "grade": "B-",
          "instructor": "Prof. Wilson",
          "issued_at": "2023-10-30T23:12:03.06138606Z",
          "issuer_id": "IU-PHYS",
          "started_at": "2023-08-30T14:20:01.807737711Z",
          "term_id": "Semester_1_2023"
        },
        {
          "assessed_at": "2023-11-05T05:13:10.093554002Z",
          "attempt_no": 1,
          "completed_at": "2023-10-30T05:13:10.093554002Z",
          "course_id": "IT117IU",
          "course_name": "System and Network Security",
          "credits": 4,
          "grade": "A+",
          "instructor": "Prof. Harris",
          "issued_at": "2023-11-15T05:13:10.093554002Z",
          "issuer_id": "IU-PHYS",
          "started_at": "2023-08-21T20:23:49.009669827Z",
          "term_id": "Semester_1_2023"
        },
        {
          "assessed_at": "2023-11-11T02:57:36.428881123Z",
          "attempt_no": 1,
          "completed_at": "2023-11-06T02:57:36.428881123Z",
          "course_id": "IT133IU",
          "course_name": "Mobile Application Development",
          "credits": 4,
          "grade": "A+",
          "instructor": "Prof. Smith",
          "issued_at": "2023-11-22T02:57:36.428881123Z",
          "issuer_id": "IU-CHEM",
          "started_at": "2023-08-24T05:32:55.353818694Z",
          "term_id": "Semester_1_2023"
        },
        {
          "assessed_at": "2023-10-31T06:56:36.320767774Z",
          "attempt_no": 1,
          "completed_at": "2023-10-30T06:56:36.320767774Z",
          "course_id": "CH011IU",
          "course_name": "Chemistry for Engineers",
          "credits": 3,
          "grade": "D+",
          "instructor": "Prof. Smith",
          "issued_at": "2023-11-06T06:56:36.320767774Z",
          "issuer_id": "IU-CS",
          "started_at": "2023-09-09T08:49:15.969431533Z",
          "term_id": "Semester_1_2023"
        },
        {
          "assessed_at": "2023-10-29T08:15:36.831958469Z",
          "attempt_no": 1,
          "completed_at": "2023-10-26T08:15:36.831958469Z",
          "course_id": "MA003IU",
          "course_name": "Calculus 2",
          "credits": 4,
          "grade": "B",
          "instructor": "Prof. Smith",
          "issued_at": "2023-11-07T08:15:36.831958469Z",
          "issuer_id": "IU-BUS",
          "started_at": "2023-08-31T14:34:39.94304195Z",
          "term_id": "Semester_1_2023"
        }
      ],
      "gpa": 3,
      "term_id": "Semester_1_2023",
      "total_credits": 15
    },
    "Semester_1_2024": {
      "courses": [
        {
          "assessed_at": "2024-11-09T15:02:06.432245053Z",
          "attempt_no": 1,
          "completed_at": "2024-11-06T15:02:06.432245053Z",
          "course_id": "IT069IU",
          "course_name": "Object-Oriented Programming",
          "credits": 4,
          "grade": "C+",
          "instructor": "Prof. Brown",
          "issued_at": "2024-11-13T15:02:06.432245053Z",
          "issuer_id": "IU-CS",
          "started_at": "2024-08-28T16:16:58.897181254Z",
          "term_id": "Semester_1_2024"
        },
        {
          "assessed_at": "2024-10-28T05:48:56.703288168Z",
          "attempt_no": 1,
          "completed_at": "2024-10-23T05:48:56.703288168Z",
          "course_id": "MA003IU",
          "course_name": "Calculus 2",
          "credits": 4,
          "grade": "C-",
          "instructor": "Prof. Wilson",
          "issued_at": "2024-11-08T05:48:56.703288168Z",
          "issuer_id": "IU-PHYS",
          "started_at": "2024-08-29T22:30:37.710437795Z",
          "term_id": "Semester_1_2024"
        },
        {
          "assessed_at": "2024-11-04T23:29:28.269989029Z",
          "attempt_no": 1,
          "completed_at": "2024-10-29T23:29:28.269989029Z",
          "course_id": "IT076IU",
          "course_name": "Software Engineering",
          "credits": 4,
          "grade": "B+",
          "instructor": "Prof. Thomas",
          "issued_at": "2024-11-07T23:29:28.269989029Z",
          "issuer_id": "IU-MATH",
          "started_at": "2024-09-03T09:36:21.756255432Z",
          "term_id": "Semester_1_2024"
        },
        {
          "assessed_at": "2024-10-20T13:18:44.338467963Z",
          "attempt_no": 1,
          "completed_at": "2024-10-18T13:18:44.338467963Z",
          "course_id": "CH011IU",
          "course_name": "Chemistry for Engineers",
          "credits": 3,
          "grade": "B-",
          "instructor": "Prof. Smith",
          "issued_at": "2024-10-30T13:18:44.338467963Z",
          "issuer_id": "IU-BUS",
          "started_at": "2024-09-06T03:00:46.304120245Z",
          "term_id": "Semester_1_2024"
        },
        {
          "assessed_at": "2024-11-03T00:48:52.944005231Z",
          "attempt_no": 1,
          "completed_at": "2024-10-29T00:48:52.944005231Z",
          "course_id": "PH015IU",
          "course_name": "Physics 3",
          "credits": 3,
          "grade": "A+",
          "instructor": "Prof. Johnson",
          "issued_at": "2024-11-11T00:48:52.944005231Z",
          "issuer_id": "IU-PHYS",
          "started_at": "2024-09-03T08:41:34.193906901Z",
          "term_id": "Semester_1_2024"
        }
      ],
      "gpa": 2.8,
      "term_id": "Semester_1_2024",
      "total_credits": 15
    },
    "Semester_1_2025": {
      "courses": [
        {
          "assessed_at": "2025-11-03T07:03:06.874155474Z",
          "attempt_no": 1,
          "completed_at": "2025-10-30T07:03:06.874155474Z",
          "course_id": "PE008IU",
          "course_name": "Critical Thinking",
          "credits": 3,
          "grade": "B-",
          "instructor": "Prof. White",
          "issued_at": "2025-11-12T07:03:06.874155474Z",
          "issuer_id": "IU-BUS",
          "started_at": "2025-08-15T17:33:00.115119033Z",
          "term_id": "Semester_1_2025"
        },
        {
          "assessed_at": "2025-10-26T03:37:41.891840093Z",
          "attempt_no": 1,
          "completed_at": "2025-10-21T03:37:41.891840093Z",
          "course_id": "MA001IU",
          "course_name": "Calculus 1",
          "credits": 4,
          "grade": "B+",
          "instructor": "Prof. Anderson",
          "issued_at": "2025-11-04T03:37:41.891840093Z",
          "issuer_id": "IU-CS",
          "started_at": "2025-08-19T20:36:11.236682387Z",
          "term_id": "Semester_1_2025"
        },
        {
          "assessed_at": "2025-11-09T15:15:32.721733278Z",
          "attempt_no": 1,
          "completed_at": "2025-11-07T15:15:32.721733278Z",
          "course_id": "IT134IU",
          "course_name": "Internet of Things",
          "credits": 4,
          "grade": "A+",
          "instructor": "Prof. Wilson",
          "issued_at": "2025-11-19T15:15:32.721733278Z",
          "issuer_id": "IU-CHEM",
          "started_at": "2025-08-30T01:14:45.497509319Z",
          "term_id": "Semester_1_2025"
        },
        {
          "assessed_at": "2025-10-22T11:04:31.993881915Z",
          "attempt_no": 1,
          "completed_at": "2025-10-18T11:04:31.993881915Z",
          "course_id": "IT069IU",
          "course_name": "Object-Oriented Programming",
          "credits": 4,
          "grade": "A",
          "instructor": "Prof. Jackson",
          "issued_at": "2025-11-01T11:04:31.993881915Z",
          "issuer_id": "IU-PHYS",
          "started_at": "2025-08-25T07:07:29.869361342Z",
          "term_id": "Semester_1_2025"
        },
        {
          "assessed_at": "2025-11-05T03:26:36.619089397Z",
          "attempt_no": 1,
          "completed_at": "2025-11-01T03:26:36.619089397Z",
          "course_id": "IT116IU",
          "course_name": "C/C++ Programming",
          "credits": 4,
          "grade": "A+",
          "instructor": "Prof. Wilson",
          "issued_at": "2025-11-14T03:26:36.619089397Z",
          "issuer_id": "IU-MATH",
          "started_at": "2025-08-19T11:39:40.111992857Z",
          "term_id": "Semester_1_2025"
        }
      ],
      "gpa": 3.6,
      "term_id": "Semester_1_2025",
      "total_credits": 15
    },
    "Semester_2_2023": {
      "courses": [
        {
          "assessed_at": "2024-04-04T02:48:08.376576205Z",
          "attempt_no": 1,
          "completed_at": "2024-04-01T02:48:08.376576205Z",
          "course_id": "IT133IU",
          "course_name": "Mobile Application Development",
          "credits": 4,
          "grade": "A-",
          "instructor": "Prof. Thomas",
          "issued_at": "2024-04-18T02:48:08.376576205Z",
          "issuer_id": "IU-MATH",
          "started_at": "2024-01-14T04:25:42.438285472Z",
          "term_id": "Semester_2_2023"
        },
        {
          "assessed_at": "2024-03-21T20:53:08.967325922Z",
          "attempt_no": 1,
          "completed_at": "2024-03-17T20:53:08.967325922Z",
          "course_id": "PE008IU",
          "course_name": "Critical Thinking",
          "credits": 3,
          "grade": "B-",
          "instructor": "Prof. Wilson",
          "issued_at": "2024-04-02T20:53:08.967325922Z",
          "issuer_id": "IU-BUS",
          "started_at": "2024-01-25T02:23:37.81692337Z",
          "term_id": "Semester_2_2023"
        },
        {
          "assessed_at": "2024-03-31T12:29:59.241334792Z",
          "attempt_no": 1,
          "completed_at": "2024-03-24T12:29:59.241334792Z",
          "course_id": "EN008IU",
          "course_name": "Listening AE1",
          "credits": 2,
          "grade": "C",
          "instructor": "Prof. Brown",
          "issued_at": "2024-04-03T12:29:59.241334792Z",
          "issuer_id": "IU-BUS",
          "started_at": "2024-01-16T01:47:08.118563248Z",
          "term_id": "Semester_2_2023"
        },
        {
          "assessed_at": "2024-03-17T04:24:14.651142917Z",
          "attempt_no": 1,
          "completed_at": "2024-03-15T04:24:14.651142917Z",
          "course_id": "IT117IU",
          "course_name": "System and Network Security",
          "credits": 4,
          "grade": "A-",
          "instructor": "Prof. Thomas",
          "issued_at": "2024-03-30T04:24:14.651142917Z",
          "issuer_id": "IU-PHYS",
          "started_at": "2024-01-26T23:06:39.548738127Z",
          "term_id": "Semester_2_2023"
        },
        {
          "assessed_at": "2024-03-26T17:38:55.267996198Z",
          "attempt_no": 1,
          "completed_at": "2024-03-24T17:38:55.267996198Z",
          "course_id": "IT117IU",
          "course_name": "System and Network Security",
          "credits": 4,
          "grade": "B+",
          "instructor": "Prof. Taylor",
          "issued_at": "2024-04-06T17:38:55.267996198Z",
          "issuer_id": "IU-CS",
          "started_at": "2024-01-17T03:03:34.578246828Z",
          "term_id": "Semester_2_2023"
        }
      ],
      "gpa": 3.0800000000000005,
      "term_id": "Semester_2_2023",
      "total_credits": 15
    },
    "Semester_2_2024": {
      "courses": [
        {
          "assessed_at": "2025-03-18T18:58:53.158275824Z",
          "attempt_no": 1,
          "completed_at": "2025-03-15T18:58:53.158275824Z",
          "course_id": "IT153IU",
          "course_name": "Discrete Mathematics",
          "credits": 3,
          "grade": "C+",
          "instructor": "Prof. Anderson",
          "issued_at": "2025-03-28T18:58:53.158275824Z",
          "issuer_id": "IU-BUS",
          "started_at": "2025-01-22T07:42:02.180148979Z",
          "term_id": "Semester_2_2024"
        },
        {
          "assessed_at": "2025-03-26T02:06:14.133585419Z",
          "attempt_no": 1,
          "completed_at": "2025-03-21T02:06:14.133585419Z",
          "course_id": "MA026IU",
          "course_name": "Probability, Statistic \u0026 Random Process",
          "credits": 3,
          "grade": "C-",
          "instructor": "Prof. Smith",
          "issued_at": "2025-03-28T02:06:14.133585419Z",
          "issuer_id": "IU-MATH",
          "started_at": "2025-01-12T11:25:54.014562666Z",
          "term_id": "Semester_2_2024"
        },
        {
          "assessed_at": "2025-03-20T15:23:49.37210737Z",
          "attempt_no": 1,
          "completed_at": "2025-03-13T15:23:49.37210737Z",
          "course_id": "PH015IU",
          "course_name": "Physics 3",
          "credits": 3,
          "grade": "C-",
          "instructor": "Prof. Harris",
          "issued_at": "2025-03-27T15:23:49.37210737Z",
          "issuer_id": "IU-PHYS",
          "started_at": "2025-01-17T22:33:33.99435492Z",
          "term_id": "Semester_2_2024"
        },
        {
          "assessed_at": "2025-03-31T02:28:35.600689145Z",
          "attempt_no": 1,
          "completed_at": "2025-03-30T02:28:35.600689145Z",
          "course_id": "IT091IU",
          "course_name": "Computer Networks",
          "credits": 4,
          "grade": "A-",
          "instructor": "Prof. Davis",
          "issued_at": "2025-04-01T02:28:35.600689145Z",
          "issuer_id": "IU-MATH",
          "started_at": "2025-01-10T13:41:10.071076558Z",
          "term_id": "Semester_2_2024"
        },
        {
          "assessed_at": "2025-03-20T23:56:03.000081452Z",
          "attempt_no": 1,
          "completed_at": "2025-03-19T23:56:03.000081452Z",
          "course_id": "IT116IU",
          "course_name": "C/C++ Programming",
          "credits": 4,
          "grade": "C+",
          "instructor": "Prof. Smith",
          "issued_at": "2025-03-21T23:56:03.000081452Z",
          "issuer_id": "IU-MATH",
          "started_at": "2025-01-16T07:06:43.022713993Z",
          "term_id": "Semester_2_2024"
        }
      ],
      "gpa": 2.34,
      "term_id": "Semester_2_2024",
      "total_credits": 15
    },
    "Summer_2023": {
      "courses": [
        {
          "assessed_at": "2023-07-08T16:27:08.726594803Z",
          "attempt_no": 1,
          "completed_at": "2023-07-02T16:27:08.726594803Z",
          "course_id": "IT154IU",
          "course_name": "Linear Algebra",
          "credits": 3,
          "grade": "A+",
          "instructor": "Prof. Harris",
          "issued_at": "2023-07-20T16:27:08.726594803Z",
          "issuer_id": "IU-PHYS",
          "started_at": "2023-06-12T01:50:13.730822343Z",
          "term_id": "Summer_2023"
        },
        {
          "assessed_at": "2023-07-04T13:56:29.691258689Z",
          "attempt_no": 1,
          "completed_at": "2023-06-27T13:56:29.691258689Z",
          "course_id": "IT153IU",
          "course_name": "Discrete Mathematics",
          "credits": 3,
          "grade": "A+",
          "instructor": "Prof. Johnson",
          "issued_at": "2023-07-12T13:56:29.691258689Z",
          "issuer_id": "IU-MATH",
          "started_at": "2023-06-02T17:25:30.031999915Z",
          "term_id": "Summer_2023"
        },
        {
          "assessed_at": "2023-07-09T12:26:01.379839485Z",
          "attempt_no": 1,
          "completed_at": "2023-07-02T12:26:01.379839485Z",
          "course_id": "EN007IU",
          "course_name": "Writing AE1",
          "credits": 2,
          "grade": "A",
          "instructor": "Prof. Anderson",
          "issued_at": "2023-07-21T12:26:01.379839485Z",
          "issuer_id": "IU-PHYS",
          "started_at": "2023-06-06T15:55:39.876987777Z",
          "term_id": "Summer_2023"
        },
        {
          "assessed_at": "2023-07-01T08:44:07.917619115Z",
          "attempt_no": 1,
          "completed_at": "2023-06-28T08:44:07.917619115Z",
          "course_id": "IT117IU",
          "course_name": "System and Network Security",
          "credits": 4,
          "grade": "A-",
          "instructor": "Prof. White",
          "issued_at": "2023-07-09T08:44:07.917619115Z",
          "issuer_id": "IU-MATH",
          "started_at": "2023-06-07T20:13:28.143957031Z",
          "term_id": "Summer_2023"
        },
        {
          "assessed_at": "2023-07-08T07:38:12.214142252Z",
          "attempt_no": 1,
          "completed_at": "2023-07-02T07:38:12.214142252Z",
          "course_id": "IT134IU",
          "course_name": "Internet of Things",
          "credits": 4,
          "grade": "B-",
          "instructor": "Prof. Miller",
          "issued_at": "2023-07-21T07:38:12.214142252Z",
          "issuer_id": "IU-PHYS",
          "started_at": "2023-06-07T08:49:42.78510578Z",
          "term_id": "Summer_2023"
        }
      ],
      "gpa": 3.6799999999999997,
      "term_id": "Summer_2023",
      "total_credits": 15
    },
    "Summer_2024": {
      "courses": [
        {
          "assessed_at": "2024-07-07T13:50:43.64708649Z",
          "attempt_no": 1,
          "completed_at": "2024-07-01T13:50:43.64708649Z",
          "course_id": "IT064IU",
          "course_name": "Introduction to Computing",
          "credits": 3,
          "grade": "B",
          "instructor": "Prof. Miller",
          "issued_at": "2024-07-13T13:50:43.64708649Z",
          "issuer_id": "IU-CHEM",
          "started_at": "2024-06-06T23:52:03.613921788Z",
          "term_id": "Summer_2024"
        },
        {
          "assessed_at": "2024-07-01T03:30:59.473477093Z",
          "attempt_no": 1,
          "completed_at": "2024-06-30T03:30:59.473477093Z",
          "course_id": "PH014IU",
          "course_name": "Physics 2",
          "credits": 2,
          "grade": "D+",
          "instructor": "Prof. Taylor",
          "issued_at": "2024-07-14T03:30:59.473477093Z",
          "issuer_id": "IU-CS",
          "started_at": "2024-06-07T21:33:56.130575332Z",
          "term_id": "Summer_2024"
        },
        {
          "assessed_at": "2024-07-04T11:02:45.694848667Z",
          "attempt_no": 1,
          "completed_at": "2024-06-30T11:02:45.694848667Z",
          "course_id": "IT116IU",
          "course_name": "C/C++ Programming",
          "credits": 4,
          "grade": "B+",
          "instructor": "Prof. Smith",
          "issued_at": "2024-07-12T11:02:45.694848667Z",
          "issuer_id": "IU-PHYS",
          "started_at": "2024-06-06T22:02:36.218971848Z",
          "term_id": "Summer_2024"
        },
        {
          "assessed_at": "2024-06-28T14:57:05.371792404Z",
          "attempt_no": 1,
          "completed_at": "2024-06-27T14:57:05.371792404Z",
          "course_id": "MA026IU",
          "course_name": "Probability, Statistic \u0026 Random Process",
          "credits": 3,
          "grade": "C",
          "instructor": "Prof. Johnson",
          "issued_at": "2024-07-09T14:57:05.371792404Z",
          "issuer_id": "IU-MATH",
          "started_at": "2024-06-04T20:06:26.894848602Z",
          "term_id": "Summer_2024"
        },
        {
          "assessed_at": "2024-07-05T03:37:10.055095496Z",
          "attempt_no": 1,
          "completed_at": "2024-06-30T03:37:10.055095496Z",
          "course_id": "IT064IU",
          "course_name": "Introduction to Computing",
          "credits": 3,
          "grade": "A",
          "instructor": "Prof. Miller",
          "issued_at": "2024-07-07T03:37:10.055095496Z",
          "issuer_id": "IU-CHEM",
          "started_at": "2024-06-11T06:56:08.368309227Z",
          "term_id": "Summer_2024"
        }
      ],
      "gpa": 2.7199999999999998,
      "term_id": "Summer_2024",
      "total_credits": 15
    }
  }
}
