{
  "student_id": "did:example:ITITIU00060",
  "terms": {
    "Semester_1_2023": {
      "courses": [
        {
          "assessed_at": "2023-10-26T04:46:36.382434194Z",
          "attempt_no": 1,
          "completed_at": "2023-10-21T04:46:36.382434194Z",
          "course_id": "IT069IU",
          "course_name": "Object-Oriented Programming",
          "credits": 4,
          "grade": "B",
          "instructor": "Prof. Brown",
          "issued_at": "2023-11-07T04:46:36.382434194Z",
          "issuer_id": "IU-BUS",
          "started_at": "2023-09-02T08:32:57.34893066Z",
          "term_id": "Semester_1_2023"
        },
        {
          "assessed_at": "2023-11-13T07:45:42.964313356Z",
          "attempt_no": 1,
          "completed_at": "2023-11-06T07:45:42.964313356Z",
          "course_id": "CH011IU",
          "course_name": "Chemistry for Engineers",
          "credits": 3,
          "grade": "D",
          "instructor": "Prof. Wilson",
          "issued_at": "2023-11-19T07:45:42.964313356Z",
          "issuer_id": "IU-PHYS",
          "started_at": "2023-08-27T21:23:59.988071255Z",
          "term_id": "Semester_1_2023"
        },
        {
          "assessed_at": "2023-10-21T04:31:24.627056013Z",
          "attempt_no": 1,
          "completed_at": "2023-10-20T04:31:24.627056013Z",
          "course_id": "MA026IU",
          "course_name": "Probability, Statistic \u0026 Random Process",
          "credits": 3,
          "grade": "A",
          "instructor": "Prof. Taylor",
          "issued_at": "2023-10-30T04:31:24.627056013Z",
          "issuer_id": "IU-BUS",
          "started_at": "2023-09-09T02:04:03.280687167Z",
          "term_id": "Semester_1_2023"
        },
        {
          "assessed_at": "2023-11-05T10:32:55.623619137Z",
          "attempt_no": 1,
          "completed_at": "2023-11-03T10:32:55.623619137Z",
          "course_id": "PH015IU",
          "course_name": "Physics 3",
          "credits": 3,
          "grade": "A+",
          "instructor": "Prof. Johnson",
          "issued_at": "2023-11-08T10:32:55.623619137Z",
          "issuer_id": "IU-CS",
          "started_at": "2023-08-25T15:08:22.354085098Z",
          "term_id": "Semester_1_2023"
        },
        {
          "assessed_at": "2023-11-11T19:49:02.187360315Z",
          "attempt_no": 1,
          "completed_at": "2023-11-07T19:49:02.187360315Z",
          "course_id": "PE008IU",
          "course_name": "Critical Thinking",
          "credits": 3,
          "grade": "A-",
          "instructor": "Prof. Wilson",
          "issued_at": "2023-11-13T19:49:02.187360315Z",
          "issuer_id": "IU-CHEM",
          "started_at": "2023-08-17T14:14:52.355475865Z",
          "term_id": "Semester_1_2023"
        },
        {
          "assessed_at": "2023-11-09T13:42:11.473712008Z",
          "attempt_no": 1,
          "completed_at": "2023-11-05T13:42:11.473712008Z",
          "course_id": "IT069IU",
          "course_name": "Object-Oriented Programming",
          "credits": 4,
          "grade": "C",
          "instructor": "Prof. Anderson",
          "issued_at": "2023-11-14T13:42:11.473712008Z",
          "issuer_id": "IU-BUS",
          "started_at": "2023-08-31T16:42:22.676047659Z",
          "term_id": "Semester_1_2023"
        }
      ],
      "gpa": 2.9499999999999997,
      "term_id": "Semester_1_2023",
      "total_credits": 18
    },
    "Semester_1_2024": {
      "courses": [
        {
          "assessed_at": "2024-11-12T10:06:47.440441919Z",
          "attempt_no": 1,
          "completed_at": "2024-11-05T10:06:47.440441919Z",
          "course_id": "IT064IU",
          "course_name": "Introduction to Computing",
          "credits": 3,
          "grade": "B-",
          "instructor": "Prof. White",
          "issued_at": "2024-11-26T10:06:47.440441919Z",
          "issuer_id": "IU-PHYS",
          "started_at": "2024-08-23T03:54:21.457515036Z",
          "term_id": "Semester_1_2024"
        },
        {
          "assessed_at": "2024-11-08T17:57:56.84602059Z",
          "attempt_no": 1,
          "completed_at": "2024-11-02T17:57:56.84602059Z",
          "course_id": "PH014IU",
          "course_name": "Physics 2",
          "credits": 2,
          "grade": "B-",
          "instructor": "Prof. Anderson",
          "issued_at": "2024-11-17T17:57:56.84602059Z",
          "issuer_id": "IU-PHYS",
          "started_at": "2024-08-24T21:42:09.003081122Z",
          "term_id": "Semester_1_2024"
        },
        {
          "assessed_at": "2024-10-29T14:37:56.28323652Z",
          "attempt_no": 1,
          "completed_at": "2024-10-27T14:37:56.28323652Z",
          "course_id": "IT064IU",
          "course_name": "Introduction to Computing",
          "credits": 3,
          "grade": "B+",
          "instructor": "Prof. Taylor",
          "issued_at": "2024-11-01T14:37:56.28323652Z",
          "issuer_id": "IU-CHEM",
          "started_at": "2024-08-26T18:40:26.002796259Z",
          "term_id": "Semester_1_2024"
        },
        {
          "assessed_at": "2024-11-09T14:57:01.846336006Z",
          "attempt_no": 1,
          "completed_at": "2024-11-03T14:57:01.846336006Z",
          "course_id": "IT076IU",
          "course_name": "Software Engineering",
          "credits": 4,
          "grade": "C-",
          "instructor": "Prof. Thomas",
          "issued_at": "2024-11-16T14:57:01.846336006Z",
          "issuer_id": "IU-CHEM",
          "started_at": "2024-09-05T07:07:01.772489381Z",
          "term_id": "Semester_1_2024"
        },
        {
          "assessed_at": "2024-10-23T00:56:20.669010515Z",
          "attempt_no": 1,
          "completed_at": "2024-10-22T00:56:20.669010515Z",
          "course_id": "IT133IU",
          "course_name": "Mobile Application Development",
          "credits": 4,
          "grade": "B",
          "instructor": "Prof. Wilson",
          "issued_at": "2024-10-30T00:56:20.669010515Z",
          "issuer_id": "IU-CHEM",
          "started_at": "2024-08-22T20:32:41.739865101Z",
          "term_id": "Semester_1_2024"
        },
        {
          "assessed_at": "2024-10-27T06:59:46.398420493Z",
          "attempt_no": 1,
          "completed_at": "2024-10-26T06:59:46.398420493Z",
          "course_id": "IT154IU",
          "course_name": "Linear Algebra",
          "credits": 3,
          "grade": "C",
          "instructor": "Prof. White",
          "issued_at": "2024-11-09T06:59:46.398420493Z",
          "issuer_id": "IU-MATH",
          "started_at": "2024-08-23T13:34:08.55685049Z",
          "term_id": "Semester_1_2024"
        }
      ],
      "gpa": 2.5666666666666664,
      "term_id": "Semester_1_2024",
      "total_credits": 18
    },
    "Semester_1_2025": {
      "courses": [
        {
          "assessed_at": "2025-11-03T03:57:08.727492719Z",
          "attempt_no": 1,
          "completed_at": "2025-10-31T03:57:08.727492719Z",
          "course_id": "IT116IU",
          "course_name": "C/C++ Programming",
          "credits": 4,
          "grade": "B",
          "instructor": "Prof. Wilson",
          "issued_at": "2025-11-17T03:57:08.727492719Z",
          "issuer_id": "IU-CS",
          "started_at": "2025-09-01T02:38:25.759350973Z",
          "term_id": "Semester_1_2025"
        },
        {
          "assessed_at": "2025-10-28T08:52:51.249433714Z",
          "attempt_no": 1,
          "completed_at": "2025-10-23T08:52:51.249433714Z",
          "course_id": "IT064IU",
          "course_name": "Introduction to Computing",
          "credits": 3,
          "grade": "C",
          "instructor": "Prof. Anderson",
          "issued_at": "2025-10-31T08:52:51.249433714Z",
          "issuer_id": "IU-BUS",
          "started_at": "2025-08-15T01:26:24.645996783Z",
          "term_id": "Semester_1_2025"
        },
        {
          "assessed_at": "2025-11-11T19:08:02.478775347Z",
          "attempt_no": 1,
          "completed_at": "2025-11-06T19:08:02.478775347Z",
          "course_id": "IT064IU",
          "course_name": "Introduction to Computing",
          "credits": 3,
          "grade": "A-",
          "instructor": "Prof. Thomas",
          "issued_at": "2025-11-18T19:08:02.478775347Z",
          "issuer_id": "IU-PHYS",
          "started_at": "2025-09-05T21:41:21.291958027Z",
          "term_id": "Semester_1_2025"
        },
        {
          "assessed_at": "2025-10-27T00:27:04.773397914Z",
          "attempt_no": 1,
          "completed_at": "2025-10-22T00:27:04.773397914Z",
          "course_id": "PH014IU",
          "course_name": "Physics 2",
          "credits": 2,
          "grade": "A+",
          "instructor": "Prof. White",
          "issued_at": "2025-11-02T00:27:04.773397914Z",
          "issuer_id": "IU-BUS",
          "started_at": "2025-08-28T01:25:09.150049662Z",
          "term_id": "Semester_1_2025"
        },
        {
          "assessed_at": "2025-10-27T02:29:35.597758278Z",
          "attempt_no": 1,
          "completed_at": "2025-10-21T02:29:35.597758278Z",
          "course_id": "PH014IU",
          "course_name": "Physics 2",
          "credits": 2,
          "grade": "A-",
          "instructor": "Prof. Johnson",
          "issued_at": "2025-10-28T02:29:35.597758278Z",
          "issuer_id": "IU-PHYS",
          "started_at": "2025-09-02T02:59:05.482380339Z",
          "term_id": "Semester_1_2025"
        },
        {
          "assessed_at": "2025-10-26T20:42:37.213635553Z",
          "attempt_no": 1,
          "completed_at": "2025-10-21T20:42:37.213635553Z",
          "course_id": "IT160IU",
          "course_name": "Data Mining",
          "credits": 4,
          "grade": "A",
          "instructor": "Prof. Thomas",
          "issued_at": "2025-10-30T20:42:37.213635553Z",
          "issuer_id": "IU-CHEM",
          "started_at": "2025-08-31T06:36:44.936929462Z",
          "term_id": "Semester_1_2025"
        }
      ],
      "gpa": 3.4,
      "term_id": "Semester_1_2025",
      "total_credits": 18
    },
    "Semester_2_2023": {
      "courses": [
        {
          "assessed_at": "2024-03-29T19:12:36.955437862Z",
          "attempt_no": 1,
          "completed_at": "2024-03-24T19:12:36.955437862Z",
          "course_id": "IT160IU",
          "course_name": "Data Mining",
          "credits": 4,
          "grade": "C-",
          "instructor": "Prof. Brown",
          "issued_at": "2024-04-09T19:12:36.955437862Z",
          "issuer_id": "IU-PHYS",
          "started_at": "2024-01-24T23:56:37.163906844Z",
          "term_id": "Semester_2_2023"
        },
        {
          "assessed_at": "2024-03-26T04:02:27.711262162Z",
          "attempt_no": 1,
          "completed_at": "2024-03-24T04:02:27.711262162Z",
          "course_id": "IT067IU",
          "course_name": "Digital Logic Design",
          "credits": 3,
          "grade": "D+",
          "instructor": "Prof. Brown",
          "issued_at": "2024-04-03T04:02:27.711262162Z",
          "issuer_id": "IU-CHEM",
          "started_at": "2024-01-22T01:37:22.715074446Z",
          "term_id": "Semester_2_2023"
        },
        {
          "assessed_at": "2024-03-27T01:56:40.932083323Z",
          "attempt_no": 1,
          "completed_at": "2024-03-22T01:56:40.932083323Z",
          "course_id": "EN008IU",
          "course_name": "Listening AE1",
          "credits": 2,
          "grade": "C",
          "instructor": "Prof. Anderson",
          "issued_at": "2024-04-08T01:56:40.932083323Z",
          "issuer_id": "IU-PHYS",
          "started_at": "2024-01-20T15:52:56.068145417Z",
          "term_id": "Semester_2_2023"
        },
        {
          "assessed_at": "2024-03-28T19:26:05.788206355Z",
          "attempt_no": 1,
          "completed_at": "2024-03-23T19:26:05.788206355Z",
          "course_id": "IT076IU",
          "course_name": "Software Engineering",
          "credits": 4,
          "grade": "B-",
          "instructor": "Prof. Johnson",
          "issued_at": "2024-04-02T19:26:05.788206355Z",
          "issuer_id": "IU-CS",
          "started_at": "2024-02-02T05:43:17.260720739Z",
          "term_id": "Semester_2_2023"
        },
        {
          "assessed_at": "2024-03-29T08:29:43.895341585Z",
          "attempt_no": 1,
          "completed_at": "2024-03-28T08:29:43.895341585Z",
          "course_id": "IT067IU",
          "course_name": "Digital Logic Design",
          "credits": 3,
          "grade": "D+",
          "instructor": "Prof. Johnson",
          "issued_at": "2024-04-06T08:29:43.895341585Z",
          "issuer_id": "IU-MATH",
          "started_at": "2024-01-12T15:47:33.04636175Z",
          "term_id": "Semester_2_2023"
        },
        {
          "assessed_at": "2024-03-26T02:43:50.299246419Z",
          "attempt_no": 1,
          "completed_at": "2024-03-22T02:43:50.299246419Z",
          "course_id": "EN008IU",
          "course_name": "Listening AE1",
          "credits": 2,
          "grade": "D",
          "instructor": "Prof. Thomas",
          "issued_at": "2024-04-08T02:43:50.299246419Z",
          "issuer_id": "IU-CHEM",
          "started_at": "2024-01-13T06:59:31.730345358Z",
          "term_id": "Semester_2_2023"
        }
      ],
      "gpa": 1.6666666666666667,
      "term_id": "Semester_2_2023",
      "total_credits": 18
    },
    "Semester_2_2024": {
      "courses": [
        {
          "assessed_at": "2025-03-26T08:44:42.304486435Z",
          "attempt_no": 1,
          "completed_at": "2025-03-22T08:44:42.304486435Z",
          "course_id": "IT013IU",
          "course_name": "Algorithms \u0026 Data Structures",
          "credits": 4,
          "grade": "B-",
          "instructor": "Prof. Smith",
          "issued_at": "2025-04-07T08:44:42.304486435Z",
          "issuer_id": "IU-CHEM",
          "started_at": "2025-01-19T15:09:16.850358109Z",
          "term_id": "Semester_2_2024"
        },
        {
          "assessed_at": "2025-03-29T08:12:56.873532115Z",
          "attempt_no": 1,
          "completed_at": "2025-03-28T08:12:56.873532115Z",
          "course_id": "PH015IU",
          "course_name": "Physics 3",
          "credits": 3,
          "grade": "A",
          "instructor": "Prof. Smith",
          "issued_at": "2025-03-31T08:12:56.873532115Z",
          "issuer_id": "IU-CS",
          "started_at": "2025-01-17T13:27:07.186685078Z",
          "term_id": "Semester_2_2024"
        },
        {
          "assessed_at": "2025-03-19T17:48:37.794484721Z",
          "attempt_no": 1,
          "completed_at": "2025-03-16T17:48:37.794484721Z",
          "course_id": "CH011IU",
          "course_name": "Chemistry for Engineers",
          "credits": 3,
          "grade": "D+",
          "instructor": "Prof. Wilson",
          "issued_at": "2025-04-01T17:48:37.794484721Z",
          "issuer_id": "IU-MATH",
          "started_at": "2025-01-18T14:47:23.105559786Z",
          "term_id": "Semester_2_2024"
        },
        {
          "assessed_at": "2025-04-09T05:40:58.109231323Z",
          "attempt_no": 1,
          "completed_at": "2025-04-03T05:40:58.109231323Z",
          "course_id": "IT154IU",
          "course_name": "Linear Algebra",
          "credits": 3,
          "grade": "B",
          "instructor": "Prof. Smith",
          "issued_at": "2025-04-22T05:40:58.109231323Z",
          "issuer_id": "IU-CS",
          "started_at": "2025-01-19T15:06:28.578950949Z",
          "term_id": "Semester_2_2024"
        },
        {
          "assessed_at": "2025-03-26T07:15:40.183263454Z",
          "attempt_no": 1,
          "completed_at": "2025-03-21T07:15:40.183263454Z",
          "course_id": "EN008IU",
          "course_name": "Listening AE1",
          "credits": 2,
          "grade": "A-",
          "instructor": "Prof. Davis",
          "issued_at": "2025-04-02T07:15:40.183263454Z",
          "issuer_id": "IU-CHEM",
          "started_at": "2025-01-29T11:55:28.107124878Z",
          "term_id": "Semester_2_2024"
        },
        {
          "assessed_at": "2025-03-18T23:49:44.025113775Z",
          "attempt_no": 1,
          "completed_at": "2025-03-13T23:49:44.025113775Z",
          "course_id": "IT069IU",
          "course_name": "Object-Oriented Programming",
          "credits": 4,
          "grade": "C",
          "instructor": "Prof. Harris",
          "issued_at": "2025-03-30T23:49:44.025113775Z",
          "issuer_id": "IU-PHYS",
          "started_at": "2025-01-14T09:36:22.910346874Z",
          "term_id": "Semester_2_2024"
        }
      ],
      "gpa": 2.783333333333333,
      "term_id": "Semester_2_2024",
      "total_credits": 18
    },
    "Summer_2023": {
      "courses": [
        {
          "assessed_at": "2023-07-03T11:10:32.190790767Z",
          "attempt_no": 1,
          "completed_at": "2023-06-30T11:10:32.190790767Z",
          "course_id": "PE008IU",
          "course_name": "Critical Thinking",
          "credits": 3,
          "grade": "D",
          "instructor": "Prof. Miller",
          "issued_at": "2023-07-05T11:10:32.190790767Z",
          "issuer_id": "IU-PHYS",
          "started_at": "2023-06-06T16:10:56.438918337Z",
          "term_id": "Summer_2023"
        },
        {
          "assessed_at": "2023-07-09T06:47:00.07167802Z",
          "attempt_no": 1,
          "completed_at": "2023-07-02T06:47:00.07167802Z",
          "course_id": "EN008IU",
          "course_name": "Listening AE1",
          "credits": 2,
          "grade": "D",
          "instructor": "Prof. Jackson",
          "issued_at": "2023-07-17T06:47:00.07167802Z",
          "issuer_id": "IU-BUS",
          "started_at": "2023-06-04T22:05:24.892090882Z",
          "term_id": "Summer_2023"
        },
        {
          "assessed_at": "2023-07-06T09:16:41.582862098Z",
          "attempt_no": 1,
          "completed_at": "2023-06-29T09:16:41.582862098Z",
          "course_id": "EN008IU",
          "course_name": "Listening AE1",
          "credits": 2,
          "grade": "C-",
          "instructor": "Prof. Miller",
          "issued_at": "2023-07-17T09:16:41.582862098Z",
          "issuer_id": "IU-PHYS",
          "started_at": "2023-06-03T18:24:06.120350679Z",
          "term_id": "Summer_2023"
        },
        {
          "assessed_at": "2023-07-03T19:32:57.474143221Z",
          "attempt_no": 1,
          "completed_at": "2023-06-26T19:32:57.474143221Z",
          "course_id": "EN007IU",
          "course_name": "Writing AE1",
          "credits": 2,
          "grade": "B",
          "instructor": "Prof. Wilson",
          "issued_at": "2023-07-07T19:32:57.474143221Z",
          "issuer_id": "IU-MATH",
          "started_at": "2023-06-10T17:03:16.655204555Z",
          "term_id": "Summer_2023"
        },
        {
          "assessed_at": "2023-07-02T20:27:23.420646069Z",
          "attempt_no": 1,
          "completed_at": "2023-06-30T20:27:23.420646069Z",
          "course_id": "IT091IU",
          "course_name": "Computer Networks",
          "credits": 4,
          "grade": "A-",
          "instructor": "Prof. Jackson",
          "issued_at": "2023-07-16T20:27:23.420646069Z",
          "issuer_id": "IU-BUS",
          "started_at": "2023-06-01T03:00:48.677113343Z",
          "term_id": "Summer_2023"
        },
        {
          "assessed_at": "2023-07-06T04:46:52.670356127Z",
          "attempt_no": 1,
          "completed_at": "2023-06-30T04:46:52.670356127Z",
          "course_id": "IT067IU",
          "course_name": "Digital Logic Design",
          "credits": 3,
          "grade": "C-",
          "instructor": "Prof. Davis",
          "issued_at": "2023-07-08T04:46:52.670356127Z",
          "issuer_id": "IU-MATH",
          "started_at": "2023-06-09T07:46:58.818632062Z",
          "term_id": "Summer_2023"
        }
      ],
      "gpa": 2.0166666666666666,
      "term_id": "Summer_2023",
      "total_credits": 18
    },
    "Summer_2024": {
      "courses": [
        {
          "assessed_at": "2024-07-05T18:57:08.735121981Z",
          "attempt_no": 1,
          "completed_at": "2024-06-28T18:57:08.735121981Z",
          "course_id": "EN008IU",
          "course_name": "Listening AE1",
          "credits": 2,
          "grade": "B+",
          "instructor": "Prof. Thomas",
          "issued_at": "2024-07-09T18:57:08.735121981Z",
          "issuer_id": "IU-PHYS",
          "started_at": "2024-06-02T00:27:17.125276759Z",
          "term_id": "Summer_2024"
        },
        {
          "assessed_at": "2024-07-03T21:55:25.460322321Z",
          "attempt_no": 1,
          "completed_at": "2024-07-02T21:55:25.460322321Z",
          "course_id": "IT013IU",
          "course_name": "Algorithms \u0026 Data Structures",
          "credits": 4,
          "grade": "B-",
          "instructor": "Prof. Wilson",
          "issued_at": "2024-07-06T21:55:25.460322321Z",
          "issuer_id": "IU-PHYS",
          "started_at": "2024-06-08T07:59:32.713135866Z",
          "term_id": "Summer_2024"
        },
        {
          "assessed_at": "2024-07-06T23:24:31.977142815Z",
          "attempt_no": 1,
          "completed_at": "2024-06-29T23:24:31.977142815Z",
          "course_id": "CH011IU",
          "course_name": "Chemistry for Engineers",
          "credits": 3,
          "grade": "B+",
          "instructor": "Prof. Miller",
          "issued_at": "2024-07-15T23:24:31.977142815Z",
          "issuer_id": "IU-CHEM",
          "started_at": "2024-06-02T06:59:26.752831843Z",
          "term_id": "Summer_2024"
        },
        {
          "assessed_at": "2024-06-30T22:22:58.954076667Z",
          "attempt_no": 1,
          "completed_at": "2024-06-29T22:22:58.954076667Z",
          "course_id": "IT067IU",
          "course_name": "Digital Logic Design",
          "credits": 3,
          "grade": "A-",
          "instructor": "Prof. Miller",
          "issued_at": "2024-07-10T22:22:58.954076667Z",
          "issuer_id": "IU-BUS",
          "started_at": "2024-06-08T05:23:00.00069253Z",
          "term_id": "Summer_2024"
        },
        {
          "assessed_at": "2024-07-07T18:04:24.841895119Z",
          "attempt_no": 1,
          "completed_at": "2024-07-01T18:04:24.841895119Z",
          "course_id": "MA003IU",
          "course_name": "Calculus 2",
          "credits": 4,
          "grade": "B",
          "instructor": "Prof. Brown",
          "issued_at": "2024-07-12T18:04:24.841895119Z",
          "issuer_id": "IU-PHYS",
          "started_at": "2024-06-07T21:01:45.092529817Z",
          "term_id": "Summer_2024"
        },
        {
          "assessed_at": "2024-07-04T13:41:18.219175083Z",
          "attempt_no": 1,
          "completed_at": "2024-06-27T13:41:18.219175083Z",
          "course_id": "IT154IU",
          "course_name": "Linear Algebra",
          "credits": 3,
          "grade": "C+",
          "instructor": "Prof. Jackson",
          "issued_at": "2024-07-10T13:41:18.219175083Z",
          "issuer_id": "IU-PHYS",
          "started_at": "2024-06-06T00:30:08.125508613Z",
          "term_id": "Summer_2024"
        }
      ],
      "gpa": 3.0500000000000003,
      "term_id": "Summer_2024",
      "total_credits": 18
    }
  }
}
