{
  "student_id": "did:example:ITITIU00028",
  "term_id": "Semester_1_2024",
  "courses": [
    {
      "issuer_id": "IU-BUS",
      "student_id": "ITITIU00028",
      "term_id": "Semester_1_2024",
      "course_id": "CH011IU",
      "course_name": "Chemistry for Engineers",
      "attempt_no": 1,
      "started_at": "2024-09-08T23:20:07.68683516Z",
      "completed_at": "2024-11-03T16:47:40.160339613Z",
      "assessed_at": "2024-11-08T16:47:40.160339613Z",
      "issued_at": "2024-11-09T16:47:40.160339613Z",
      "grade": "B+",
      "credits": 3,
      "instructor": "Prof. Taylor"
    },
    {
      "issuer_id": "IU-BUS",
      "student_id": "ITITIU00028",
      "term_id": "Semester_1_2024",
      "course_id": "CH011IU",
      "course_name": "Chemistry for Engineers",
      "attempt_no": 1,
      "started_at": "2024-08-21T15:47:17.820089549Z",
      "completed_at": "2024-11-04T08:30:54.197119026Z",
      "assessed_at": "2024-11-08T08:30:54.197119026Z",
      "issued_at": "2024-11-09T08:30:54.197119026Z",
      "grade": "A",
      "credits": 3,
      "instructor": "Prof. Brown"
    },
    {
      "issuer_id": "IU-CHEM",
      "student_id": "ITITIU00028",
      "term_id": "Semester_1_2024",
      "course_id": "EN007IU",
      "course_name": "Writing AE1",
      "attempt_no": 1,
      "started_at": "2024-08-26T12:08:07.682751551Z",
      "completed_at": "2024-11-05T14:37:40.842184419Z",
      "assessed_at": "2024-11-10T14:37:40.842184419Z",
      "issued_at": "2024-11-23T14:37:40.842184419Z",
      "grade": "D+",
      "credits": 2,
      "instructor": "Prof. Brown"
    },
    {
      "issuer_id": "IU-PHYS",
      "student_id": "ITITIU00028",
      "term_id": "Semester_1_2024",
      "course_id": "EN008IU",
      "course_name": "Listening AE1",
      "attempt_no": 1,
      "started_at": "2024-08-31T22:42:09.099691254Z",
      "completed_at": "2024-10-22T15:50:50.499185927Z",
      "assessed_at": "2024-10-23T15:50:50.499185927Z",
      "issued_at": "2024-10-28T15:50:50.499185927Z",
      "grade": "A-",
      "credits": 2,
      "instructor": "Prof. Brown"
    },
    {
      "issuer_id": "IU-CS",
      "student_id": "ITITIU00028",
      "term_id": "Semester_1_2024",
      "course_id": "IT134IU",
      "course_name": "Internet of Things",
      "attempt_no": 1,
      "started_at": "2024-09-01T10:59:44.913234741Z",
      "completed_at": "2024-10-27T03:38:20.240232456Z",
      "assessed_at": "2024-11-01T03:38:20.240232456Z",
      "issued_at": "2024-11-09T03:38:20.240232456Z",
      "grade": "A+",
      "credits": 4,
      "instructor": "Prof. Miller"
    },
    {
      "issuer_id": "IU-CHEM",
      "student_id": "ITITIU00028",
      "term_id": "Semester_1_2024",
      "course_id": "PH015IU",
      "course_name": "Physics 3",
      "attempt_no": 1,
      "started_at": "2024-09-08T07:15:03.469115632Z",
      "completed_at": "2024-10-25T14:13:33.320956087Z",
      "assessed_at": "2024-10-26T14:13:33.320956087Z",
      "issued_at": "2024-10-29T14:13:33.320956087Z",
      "grade": "C-",
      "credits": 3,
      "instructor": "Prof. Anderson"
    }
  ],
  "root": [
    142,
    57,
    253,
    42,
    196,
    247,
    188,
    4,
    224,
    7,
    242,
    175,
    235,
    41,
    37,
    21,
    141,
    130,
    5,
    104,
    76,
    189,
    196,
    190,
    171,
    15,
    131,
    127,
    50,
    71,
    216,
    165
  ],
  "leaves": [
    {
      "course": {
        "issuer_id": "IU-BUS",
        "student_id": "ITITIU00028",
        "term_id": "Semester_1_2024",
        "course_id": "CH011IU",
        "course_name": "Chemistry for Engineers",
        "attempt_no": 1,
        "started_at": "2024-09-08T23:20:07.68683516Z",
        "completed_at": "2024-11-03T16:47:40.160339613Z",
        "assessed_at": "2024-11-08T16:47:40.160339613Z",
        "issued_at": "2024-11-09T16:47:40.160339613Z",
        "grade": "B+",
        "credits": 3,
        "instructor": "Prof. Taylor"
      },
      "timestamp32": [
        0,
        0,
        0,
        0,
        102,
        222,
        49,
        39,
        0,
        0,
        0,
        0,
        103,
        39,
        169,
        44,
        0,
        0,
        0,
        0,
        103,
        46,
        64,
        172,
        0,
        0,
        0,
        0,
        103,
        47,
        146,
        44
      ],
      "course_hash32": [
        102,
        86,
        219,
        133,
        45,
        50,
        31,
        100,
        176,
        197,
        233,
        42,
        226,
        60,
        94,
        14,
        196,
        33,
        127,
        25,
        102,
        26,
        74,
        64,
        12,
        96,
        253,
        234,
        14,
        214,
        194,
        181
      ]
    },
    {
      "course": {
        "issuer_id": "IU-BUS",
        "student_id": "ITITIU00028",
        "term_id": "Semester_1_2024",
        "course_id": "CH011IU",
        "course_name": "Chemistry for Engineers",
        "attempt_no": 1,
        "started_at": "2024-08-21T15:47:17.820089549Z",
        "completed_at": "2024-11-04T08:30:54.197119026Z",
        "assessed_at": "2024-11-08T08:30:54.197119026Z",
        "issued_at": "2024-11-09T08:30:54.197119026Z",
        "grade": "A",
        "credits": 3,
        "instructor": "Prof. Brown"
      },
      "timestamp32": [
        0,
        0,
        0,
        0,
        102,
        198,
        12,
        5,
        0,
        0,
        0,
        0,
        103,
        40,
        134,
        62,
        0,
        0,
        0,
        0,
        103,
        45,
        204,
        62,
        0,
        0,
        0,
        0,
        103,
        47,
        29,
        190
      ],
      "course_hash32": [
        102,
        86,
        219,
        133,
        45,
        50,
        31,
        100,
        176,
        197,
        233,
        42,
        226,
        60,
        94,
        14,
        196,
        33,
        127,
        25,
        102,
        26,
        74,
        64,
        12,
        96,
        253,
        234,
        14,
        214,
        194,
        181
      ]
    },
    {
      "course": {
        "issuer_id": "IU-CHEM",
        "student_id": "ITITIU00028",
        "term_id": "Semester_1_2024",
        "course_id": "EN007IU",
        "course_name": "Writing AE1",
        "attempt_no": 1,
        "started_at": "2024-08-26T12:08:07.682751551Z",
        "completed_at": "2024-11-05T14:37:40.842184419Z",
        "assessed_at": "2024-11-10T14:37:40.842184419Z",
        "issued_at": "2024-11-23T14:37:40.842184419Z",
        "grade": "D+",
        "credits": 2,
        "instructor": "Prof. Brown"
      },
      "timestamp32": [
        0,
        0,
        0,
        0,
        102,
        204,
        112,
        39,
        0,
        0,
        0,
        0,
        103,
        42,
        45,
        180,
        0,
        0,
        0,
        0,
        103,
        48,
        197,
        52,
        0,
        0,
        0,
        0,
        103,
        65,
        232,
        180
      ],
      "course_hash32": [
        250,
        84,
        195,
        95,
        203,
        35,
        255,
        117,
        194,
        252,
        146,
        165,
        202,
        242,
        64,
        118,
        127,
        190,
        16,
        9,
        188,
        166,
        118,
        73,
        40,
        121,
        64,
        48,
        241,
        23,
        89,
        43
      ]
    },
    {
      "course": {
        "issuer_id": "IU-PHYS",
        "student_id": "ITITIU00028",
        "term_id": "Semester_1_2024",
        "course_id": "EN008IU",
        "course_name": "Listening AE1",
        "attempt_no": 1,
        "started_at": "2024-08-31T22:42:09.099691254Z",
        "completed_at": "2024-10-22T15:50:50.499185927Z",
        "assessed_at": "2024-10-23T15:50:50.499185927Z",
        "issued_at": "2024-10-28T15:50:50.499185927Z",
        "grade": "A-",
        "credits": 2,
        "instructor": "Prof. Brown"
      },
      "timestamp32": [
        0,
        0,
        0,
        0,
        102,
        211,
        156,
        65,
        0,
        0,
        0,
        0,
        103,
        23,
        201,
        218,
        0,
        0,
        0,
        0,
        103,
        25,
        27,
        90,
        0,
        0,
        0,
        0,
        103,
        31,
        178,
        218
      ],
      "course_hash32": [
        201,
        217,
        23,
        55,
        36,
        13,
        3,
        187,
        145,
        93,
        200,
        183,
        24,
        154,
        196,
        10,
        16,
        127,
        102,
        249,
        188,
        46,
        239,
        250,
        169,
        237,
        253,
        103,
        109,
        80,
        88,
        98
      ]
    },
    {
      "course": {
        "issuer_id": "IU-CS",
        "student_id": "ITITIU00028",
        "term_id": "Semester_1_2024",
        "course_id": "IT134IU",
        "course_name": "Internet of Things",
        "attempt_no": 1,
        "started_at": "2024-09-01T10:59:44.913234741Z",
        "completed_at": "2024-10-27T03:38:20.240232456Z",
        "assessed_at": "2024-11-01T03:38:20.240232456Z",
        "issued_at": "2024-11-09T03:38:20.240232456Z",
        "grade": "A+",
        "credits": 4,
        "instructor": "Prof. Miller"
      },
      "timestamp32": [
        0,
        0,
        0,
        0,
        102,
        212,
        73,
        32,
        0,
        0,
        0,
        0,
        103,
        29,
        181,
        172,
        0,
        0,
        0,
        0,
        103,
        36,
        77,
        44,
        0,
        0,
        0,
        0,
        103,
        46,
        217,
        44
      ],
      "course_hash32": [
        203,
        104,
        224,
        197,
        249,
        243,
        5,
        130,
        216,
        247,
        253,
        16,
        14,
        222,
        37,
        184,
        53,
        215,
        165,
        95,
        198,
        124,
        171,
        6,
        253,
        134,
        217,
        49,
        239,
        56,
        15,
        253
      ]
    },
    {
      "course": {
        "issuer_id": "IU-CHEM",
        "student_id": "ITITIU00028",
        "term_id": "Semester_1_2024",
        "course_id": "PH015IU",
        "course_name": "Physics 3",
        "attempt_no": 1,
        "started_at": "2024-09-08T07:15:03.469115632Z",
        "completed_at": "2024-10-25T14:13:33.320956087Z",
        "assessed_at": "2024-10-26T14:13:33.320956087Z",
        "issued_at": "2024-10-29T14:13:33.320956087Z",
        "grade": "C-",
        "credits": 3,
        "instructor": "Prof. Anderson"
      },
      "timestamp32": [
        0,
        0,
        0,
        0,
        102,
        221,
        78,
        247,
        0,
        0,
        0,
        0,
        103,
        27,
        167,
        141,
        0,
        0,
        0,
        0,
        103,
        28,
        249,
        13,
        0,
        0,
        0,
        0,
        103,
        32,
        237,
        141
      ],
      "course_hash32": [
        71,
        134,
        100,
        121,
        188,
        15,
        32,
        135,
        32,
        65,
        31,
        212,
        61,
        93,
        77,
        69,
        136,
        207,
        1,
        208,
        238,
        94,
        199,
        81,
        86,
        203,
        71,
        22,
        195,
        40,
        175,
        124
      ]
    }
  ],
  "proofs": {
    "CH011IU": [
      "96b5a699bfee84b239b52f8fcbf3a25581f8b786592369641502d9df22bdeaf9",
      "749ec20ba7b2ff725dd94599d58fe03cc95d3b01f5e4527e9a0a4ea0b53a8c9c",
      "595e06fd5de30558794d9476c6e5a722737e4f385d3adf3963291efdbdc503f7"
    ],
    "EN007IU": [
      "f1995e1f6b012b9df4e65fd6da3a4f61963f4019abae7245a46a9670ab45d18e",
      "a8f558363b5d9d34841b4d11032143a7029b6e792efe668da9e70c58a81b8882",
      "595e06fd5de30558794d9476c6e5a722737e4f385d3adf3963291efdbdc503f7"
    ],
    "EN008IU": [
      "a54396adcf56d65718d5246a483b58f30fc0906fb474bb4c5baa3a0eaab4c83d",
      "a8f558363b5d9d34841b4d11032143a7029b6e792efe668da9e70c58a81b8882",
      "595e06fd5de30558794d9476c6e5a722737e4f385d3adf3963291efdbdc503f7"
    ],
    "IT134IU": [
      "517f2c3dfbf7dd130b855928334e80dc69ace32ca6f7396c32e586088ccd2210",
      "f86e94cce007cd6275ece9fa6c56034c4bb1c692698509e16d3ef94b3b714665",
      "e6b51282a40acf4b1bfb4455947484aee5d5286db8f7d61e42fbdd733b62d177"
    ],
    "PH015IU": [
      "013b8e4c75939cb1944e60c975bd53dd3e23a4a696492b0e0d911c922e1442ee",
      "f86e94cce007cd6275ece9fa6c56034c4bb1c692698509e16d3ef94b3b714665",
      "e6b51282a40acf4b1bfb4455947484aee5d5286db8f7d61e42fbdd733b62d177"
    ]
  }
}